Workbook

Sheet 01 README
A1: Investment Analysis Toolkit — Excel Edition
A2: A formula-for-formula translation of the investment_analysis Python package. No VBA, no macros: every number is a native Excel formula you can click into and audit.
A3: Mirrors: Project 1 — Investment Analysis (Markowitz Frontier)
A5: HOW TO USE THIS WORKBOOK
A6: 1. Open in Microsoft 365 Excel | B6: Sheet '03 Raw Data' pulls live prices with STOCKHISTORY(), which needs a Microsoft 365 subscription and an internet connection. In Excel for the web, LibreOffice or a perpetual-licence version (2019/2021) those cells return a name error and nothing downstream will compute.
A7: 2. Let it calculate | B7: On first open Excel fetches ~700 days x 7 tickers. Give it a few seconds. If the sheets look empty, press Ctrl+Alt+F9 to force a full recalculation.
A8: 3. Set the risk-free rate | B8: Cell B10 on '02 Config' is the one market number that cannot be fetched by formula — STOCKHISTORY does not cover Treasury yield tickers. Enter the current 5-year Treasury yield as a decimal. The Python project pulls this automatically from ^FVX.
A9: 4. Change anything blue | B9: Tickers, dates, portfolio value, confidence levels — every blue cell is an input, and the entire workbook re-solves from it. Nothing is hardcoded downstream.
A12: SHEET MAP — WHICH PYTHON MODULE EACH SHEET REPLACES
A13: Sheet | B13: What it does | C13: Python source
A14: 02 Config | B14: All inputs: dates, tickers, risk-free rate, portfolio value, VaR confidence levels, simulation settings. | C14: config.py (AnalysisConfig) + portfolio.xlsx
A15: 03 Raw Data | B15: Live STOCKHISTORY price feed, one block per asset plus the benchmark. The only cells touching the internet. | C15: data.py — download_prices(), download_benchmark()
A16: 04 Prices | B16: Raw blocks stitched onto one shared trading calendar with INDEX/MATCH. | C16: the aligned DataFrame yfinance returns
A17: 05 Simple Returns | B17: Daily simple returns, P_t/P_(t-1) - 1. | C17: returns.py — simple_returns()
A18: 06 Log Returns | B18: Daily log returns, ln(P_t/P_(t-1)). | C18: returns.py — log_returns()
A19: 07 Annualised Inputs | B19: Annualised expected returns, the annualised covariance matrix, and the correlation matrix. | C19: optimization.py — annualized_inputs()
A20: 08 Optimisation | B20: Matrix-algebra solution: Sigma inverse, the frontier constants A/B/C/D, minimum-variance and tangency weights, the 100-point frontier. | C20: optimization.py — PortfolioMath, minimum_volatility_portfolio(), maximum_sharpe_portfolio(), efficient_frontier()
A21: 09 Monte Carlo | B21: 1,000 randomly weighted portfolios forming the feasible-set cloud. | C21: optimization.py — monte_carlo_portfolios()
A22: 10 Portfolio Returns | B22: Asset returns collapsed to one portfolio series, plus cumulative growth and the drawdown path. | C22: returns.py — portfolio_returns(); risk_metrics.py — max_drawdown()
A23: 11 Risk Metrics | B23: Beta, Alpha, Sharpe, Sortino, Calmar, Treynor, max drawdown, VaR and CVaR. | C23: risk_metrics.py (all functions)
A24: 12 Charts | B24: Price lines, the efficient frontier scatter, growth of $1 and the drawdown chart. | C24: visualization.py — plot_prices(), plot_efficient_frontier()
A27: THREE PLACES THIS WORKBOOK KNOWINGLY DIFFERS FROM THE PYTHON PROJECT
A28: Unconstrained optimisation | B28: optimization.py bounds every weight to [0, 1] and solves numerically with SciPy's SLSQP. A bounded problem has no closed form, so the matrix solution on '08 Optimisation' solves the same objective WITHOUT the bounds. Where a short position would help, these weights differ and this frontier sits slightly to the left of the Python one — constraints can never reduce risk. Everything else in the workbook is identical maths.
A29: Unadjusted closing prices | B29: data.py requests 'Adj Close', which is back-adjusted for dividends and splits. STOCKHISTORY returns the unadjusted close. Total-return figures will therefore sit slightly below the Python output for dividend-paying holdings, and a split in the sample period would show as a jump.
A30: Risk-free rate is a manual input | B30: data.download_risk_free_rate() pulls ^FVX and divides by 100. STOCKHISTORY cannot address Treasury yield tickers, so cell B10 on '02 Config' is typed in by hand.
A31: 1,000 Monte Carlo draws instead of 10,000 | B31: Purely for file size and recalculation speed. The draws are the first rows of the same numpy default_rng(42) sequence, so they match the Python simulation row for row. The frontier itself is solved analytically and does not depend on the simulation at all.
A32: Sortino ratio kept 'wrong' on purpose | B32: risk_metrics.sortino_ratio() divides an annual excess return by a DAILY downside deviation, inflating the ratio by about SQRT(252). The workbook reproduces that rather than silently correcting it, and says so on '11 Risk Metrics'.
A35: COLOUR CONVENTION
A36: Blue text on cream fill | B36: Hardcoded input — safe to edit.
A37: Black text | B37: Calculated by formula — do not overwrite.
A38: Green text | B38: A link to another sheet.
A40: Cells with a small red corner carry a comment explaining the maths and naming the Python function they come from. Hover to read them.

Sheet 02 Config
A1: Configuration & Inputs
A2: Every analysis parameter lives here. Blue cells are hardcoded inputs you may edit; black cells are formulas. Nothing downstream hardcodes a parameter.
A3: Mirrors: config.py -> AnalysisConfig dataclass
A5: MARKET DATA & PORTFOLIO PARAMETERS
A6: Parameter | B6: Value | C6: Units | D6: What it does / where it comes from in the Python project
A7: Start date | B7: 45292 | C7: date | D7: config.py: start_date = dt.datetime(2024, 1, 1). First date requested from the market data feed.
A8: End date | B8: =TODAY() | C8: date | D8: config.py: end_date = None, which main.py resolves to dt.datetime.now(). TODAY() reproduces that behaviour live.
A9: Benchmark ticker | B9: SPX | C9: text | D9: config.py: benchmark_ticker = '^GSPC'. Excel's STOCKHISTORY addresses the S&P 500 as 'SPX'. Used for Beta, Alpha and Treynor. If your Excel build rejects 'SPX', try '.INX' or 'INDEX:SPX'.
A10: Risk-free rate (annual) | B10: 0.0375 | C10: % p.a. | D10: config.py: risk_free_ticker = '^FVX' (5-year Treasury yield), taken as latest close / 100. STOCKHISTORY cannot return Treasury yield tickers, so this is a MANUAL INPUT. Update it from the current 5-year Treasury yield, entered as a decimal (4.25% -> 0.0425).
A11: Portfolio value | B11: 1000000 | C11: $ | D11: config.py: portfolio_value = 1_000_000. Converts VaR and CVaR from a return into a currency loss.
A12: Trading days per year | B12: 252 | C12: days | D12: returns.py: TRADING_DAYS_PER_YEAR = 252. The annualisation factor used everywhere.
A13: VaR confidence level 1 | B13: 0.9 | C13: % | D13: config.py: var_confidence_levels = (0.90, 0.95, 0.99).
A14: VaR confidence level 2 | B14: 0.95 | C14: % | D14: config.py: var_confidence_levels[1].
A15: VaR confidence level 3 | B15: 0.99 | C15: % | D15: config.py: var_confidence_levels[2].
A16: Monte Carlo portfolios | B16: 1000 | C16: count | D16: config.py: n_monte_carlo_portfolios = 10_000. Reduced to 1,000 here to keep the workbook responsive; the random draws used are the FIRST 1,000 draws of numpy's default_rng(42), so these rows are numerically identical to the first rows of the Python simulation.
A17: Efficient frontier points | B17: 100 | C17: count | D17: config.py: n_frontier_points = 100. Number of target returns traced along the frontier.
A18: Random seed | B18: 42 | C18: int | D18: config.py: random_seed = 42. The seed used to generate the Monte Carlo weight draws on sheet '09 Monte Carlo'.
A21: PORTFOLIO HOLDINGS
A22: Read in Python from portfolio.xlsx (single 'Ticker' column) by data.load_tickers_from_excel(). Edit these cells to change the investable universe — every sheet follows automatically.
A23: # | B23: Ticker | C23: Asset
A24: 1 | B24: JPM | C24: JPMorgan Chase & Co.
A25: 2 | B25: MS | C25: Morgan Stanley
A26: 3 | B26: BAC | C26: Bank of America Corp.
A27: 4 | B27: AAPL | C27: Apple Inc.
A28: 5 | B28: MSFT | C28: Microsoft Corp.
A29: 6 | B29: GLD | C29: SPDR Gold Shares ETF
A32: COLOUR KEY
A33: Blue = hardcoded input you may edit
A34: Black = calculated by formula
A35: Green = link to another sheet

Sheet 03 Raw Data
A1: JPM | D1: MS | G1: BAC | J1: AAPL | M1: MSFT | P1: GLD | S1: BENCHMARK
A2: Date | B2: Close | D2: Date | E2: Close | G2: Date | H2: Close | J2: Date | K2: Close | M2: Date | N2: Close | P2: Date | Q2: Close | S2: Date | T2: Close
A3: {=_xlfn.STOCKHISTORY('02 Config'!$B$24,'02 Config'!$B$7,'02 Config'!$B$8,0,0,0,1)} | D3: {=_xlfn.STOCKHISTORY('02 Config'!$B$25,'02 Config'!$B$7,'02 Config'!$B$8,0,0,0,1)} | G3: {=_xlfn.STOCKHISTORY('02 Config'!$B$26,'02 Config'!$B$7,'02 Config'!$B$8,0,0,0,1)} | J3: {=_xlfn.STOCKHISTORY('02 Config'!$B$27,'02 Config'!$B$7,'02 Config'!$B$8,0,0,0,1)} | M3: {=_xlfn.STOCKHISTORY('02 Config'!$B$28,'02 Config'!$B$7,'02 Config'!$B$8,0,0,0,1)} | P3: {=_xlfn.STOCKHISTORY('02 Config'!$B$29,'02 Config'!$B$7,'02 Config'!$B$8,0,0,0,1)} | S3: {=_xlfn.STOCKHISTORY('02 Config'!$B$9,'02 Config'!$B$7,'02 Config'!$B$8,0,0,0,1)}
A4: NOTE: STOCKHISTORY requires a Microsoft 365 subscription and an internet connection. It returns the UNADJUSTED close, whereas the Python project uses Adj Close — dividend and split adjustments aside, the two differ slightly. Each block is a single array formula in its top-left cell.

Sheet 04 Prices
A1: Aligned Price Matrix
A2: The raw blocks are stitched onto one shared trading calendar with INDEX/MATCH, so every asset and the benchmark sit on the same row for the same date. This is the single price grid the whole model reads.
A3: Mirrors: data.download_prices() returning a DataFrame: columns = tickers, index = trading dates
A4: Date | B4: JPM | C4: MS | D4: BAC | E4: AAPL | F4: MSFT | G4: GLD | H4: BENCHMARK
A5: =IFERROR(IF(OR('03 Raw Data'!A3="",'03 Raw Data'!A3=0),"",'03 Raw Data'!A3),"") | B5: =IF($A5="","",IFERROR(INDEX('03 Raw Data'!$B$3:$B$722,MATCH($A5,'03 Raw Data'!$A$3:$A$722,0)),"")) | C5: =IF($A5="","",IFERROR(INDEX('03 Raw Data'!$E$3:$E$722,MATCH($A5,'03 Raw Data'!$D$3:$D$722,0)),"")) | D5: =IF($A5="","",IFERROR(INDEX('03 Raw Data'!$H$3:$H$722,MATCH($A5,'03 Raw Data'!$G$3:$G$722,0)),"")) | E5: =IF($A5="","",IFERROR(INDEX('03 Raw Data'!$K$3:$K$722,MATCH($A5,'03 Raw Data'!$J$3:$J$722,0)),"")) | F5: =IF($A5="","",IFERROR(INDEX('03 Raw Data'!$N$3:$N$722,MATCH($A5,'03 Raw Data'!$M$3:$M$722,0)),"")) | G5: =IF($A5="","",IFERROR(INDEX('03 Raw Data'!$Q$3:$Q$722,MATCH($A5,'03 Raw Data'!$P$3:$P$722,0)),"")) | H5: =IF($A5="","",IFERROR(INDEX('03 Raw Data'!$T$3:$T$722,MATCH($A5,'03 Raw Data'!$S$3:$S$722,0)),""))
A6: =IFERROR(IF(OR('03 Raw Data'!A4="",'03 Raw Data'!A4=0),"",'03 Raw Data'!A4),"") | B6: =IF($A6="","",IFERROR(INDEX('03 Raw Data'!$B$3:$B$722,MATCH($A6,'03 Raw Data'!$A$3:$A$722,0)),"")) | C6: =IF($A6="","",IFERROR(INDEX('03 Raw Data'!$E$3:$E$722,MATCH($A6,'03 Raw Data'!$D$3:$D$722,0)),"")) | D6: =IF($A6="","",IFERROR(INDEX('03 Raw Data'!$H$3:$H$722,MATCH($A6,'03 Raw Data'!$G$3:$G$722,0)),"")) | E6: =IF($A6="","",IFERROR(INDEX('03 Raw Data'!$K$3:$K$722,MATCH($A6,'03 Raw Data'!$J$3:$J$722,0)),"")) | F6: =IF($A6="","",IFERROR(INDEX('03 Raw Data'!$N$3:$N$722,MATCH($A6,'03 Raw Data'!$M$3:$M$722,0)),"")) | G6: =IF($A6="","",IFERROR(INDEX('03 Raw Data'!$Q$3:$Q$722,MATCH($A6,'03 Raw Data'!$P$3:$P$722,0)),"")) | H6: =IF($A6="","",IFERROR(INDEX('03 Raw Data'!$T$3:$T$722,MATCH($A6,'03 Raw Data'!$S$3:$S$722,0)),""))
A7: =IFERROR(IF(OR('03 Raw Data'!A5="",'03 Raw Data'!A5=0),"",'03 Raw Data'!A5),"") | B7: =IF($A7="","",IFERROR(INDEX('03 Raw Data'!$B$3:$B$722,MATCH($A7,'03 Raw Data'!$A$3:$A$722,0)),"")) | C7: =IF($A7="","",IFERROR(INDEX('03 Raw Data'!$E$3:$E$722,MATCH($A7,'03 Raw Data'!$D$3:$D$722,0)),"")) | D7: =IF($A7="","",IFERROR(INDEX('03 Raw Data'!$H$3:$H$722,MATCH($A7,'03 Raw Data'!$G$3:$G$722,0)),"")) | E7: =IF($A7="","",IFERROR(INDEX('03 Raw Data'!$K$3:$K$722,MATCH($A7,'03 Raw Data'!$J$3:$J$722,0)),"")) | F7: =IF($A7="","",IFERROR(INDEX('03 Raw Data'!$N$3:$N$722,MATCH($A7,'03 Raw Data'!$M$3:$M$722,0)),"")) | G7: =IF($A7="","",IFERROR(INDEX('03 Raw Data'!$Q$3:$Q$722,MATCH($A7,'03 Raw Data'!$P$3:$P$722,0)),"")) | H7: =IF($A7="","",IFERROR(INDEX('03 Raw Data'!$T$3:$T$722,MATCH($A7,'03 Raw Data'!$S$3:$S$722,0)),""))
A8: =IFERROR(IF(OR('03 Raw Data'!A6="",'03 Raw Data'!A6=0),"",'03 Raw Data'!A6),"") | B8: =IF($A8="","",IFERROR(INDEX('03 Raw Data'!$B$3:$B$722,MATCH($A8,'03 Raw Data'!$A$3:$A$722,0)),"")) | C8: =IF($A8="","",IFERROR(INDEX('03 Raw Data'!$E$3:$E$722,MATCH($A8,'03 Raw Data'!$D$3:$D$722,0)),"")) | D8: =IF($A8="","",IFERROR(INDEX('03 Raw Data'!$H$3:$H$722,MATCH($A8,'03 Raw Data'!$G$3:$G$722,0)),"")) | E8: =IF($A8="","",IFERROR(INDEX('03 Raw Data'!$K$3:$K$722,MATCH($A8,'03 Raw Data'!$J$3:$J$722,0)),"")) | F8: =IF($A8="","",IFERROR(INDEX('03 Raw Data'!$N$3:$N$722,MATCH($A8,'03 Raw Data'!$M$3:$M$722,0)),"")) | G8: =IF($A8="","",IFERROR(INDEX('03 Raw Data'!$Q$3:$Q$722,MATCH($A8,'03 Raw Data'!$P$3:$P$722,0)),"")) | H8: =IF($A8="","",IFERROR(INDEX('03 Raw Data'!$T$3:$T$722,MATCH($A8,'03 Raw Data'!$S$3:$S$722,0)),""))
A9: =IFERROR(IF(OR('03 Raw Data'!A7="",'03 Raw Data'!A7=0),"",'03 Raw Data'!A7),"") | B9: =IF($A9="","",IFERROR(INDEX('03 Raw Data'!$B$3:$B$722,MATCH($A9,'03 Raw Data'!$A$3:$A$722,0)),"")) | C9: =IF($A9="","",IFERROR(INDEX('03 Raw Data'!$E$3:$E$722,MATCH($A9,'03 Raw Data'!$D$3:$D$722,0)),"")) | D9: =IF($A9="","",IFERROR(INDEX('03 Raw Data'!$H$3:$H$722,MATCH($A9,'03 Raw Data'!$G$3:$G$722,0)),"")) | E9: =IF($A9="","",IFERROR(INDEX('03 Raw Data'!$K$3:$K$722,MATCH($A9,'03 Raw Data'!$J$3:$J$722,0)),"")) | F9: =IF($A9="","",IFERROR(INDEX('03 Raw Data'!$N$3:$N$722,MATCH($A9,'03 Raw Data'!$M$3:$M$722,0)),"")) | G9: =IF($A9="","",IFERROR(INDEX('03 Raw Data'!$Q$3:$Q$722,MATCH($A9,'03 Raw Data'!$P$3:$P$722,0)),"")) | H9: =IF($A9="","",IFERROR(INDEX('03 Raw Data'!$T$3:$T$722,MATCH($A9,'03 Raw Data'!$S$3:$S$722,0)),""))
A10: =IFERROR(IF(OR('03 Raw Data'!A8="",'03 Raw Data'!A8=0),"",'03 Raw Data'!A8),"") | B10: =IF($A10="","",IFERROR(INDEX('03 Raw Data'!$B$3:$B$722,MATCH($A10,'03 Raw Data'!$A$3:$A$722,0)),"")) | C10: =IF($A10="","",IFERROR(INDEX('03 Raw Data'!$E$3:$E$722,MATCH($A10,'03 Raw Data'!$D$3:$D$722,0)),"")) | D10: =IF($A10="","",IFERROR(INDEX('03 Raw Data'!$H$3:$H$722,MATCH($A10,'03 Raw Data'!$G$3:$G$722,0)),"")) | E10: =IF($A10="","",IFERROR(INDEX('03 Raw Data'!$K$3:$K$722,MATCH($A10,'03 Raw Data'!$J$3:$J$722,0)),"")) | F10: =IF($A10="","",IFERROR(INDEX('03 Raw Data'!$N$3:$N$722,MATCH($A10,'03 Raw Data'!$M$3:$M$722,0)),"")) | G10: =IF($A10="","",IFERROR(INDEX('03 Raw Data'!$Q$3:$Q$722,MATCH($A10,'03 Raw Data'!$P$3:$P$722,0)),"")) | H10: =IF($A10="","",IFERROR(INDEX('03 Raw Data'!$T$3:$T$722,MATCH($A10,'03 Raw Data'!$S$3:$S$722,0)),""))
A11: =IFERROR(IF(OR('03 Raw Data'!A9="",'03 Raw Data'!A9=0),"",'03 Raw Data'!A9),"") | B11: =IF($A11="","",IFERROR(INDEX('03 Raw Data'!$B$3:$B$722,MATCH($A11,'03 Raw Data'!$A$3:$A$722,0)),"")) | C11: =IF($A11="","",IFERROR(INDEX('03 Raw Data'!$E$3:$E$722,MATCH($A11,'03 Raw Data'!$D$3:$D$722,0)),"")) | D11: =IF($A11="","",IFERROR(INDEX('03 Raw Data'!$H$3:$H$722,MATCH($A11,'03 Raw Data'!$G$3:$G$722,0)),"")) | E11: =IF($A11="","",IFERROR(INDEX('03 Raw Data'!$K$3:$K$722,MATCH($A11,'03 Raw Data'!$J$3:$J$722,0)),"")) | F11: =IF($A11="","",IFERROR(INDEX('03 Raw Data'!$N$3:$N$722,MATCH($A11,'03 Raw Data'!$M$3:$M$722,0)),"")) | G11: =IF($A11="","",IFERROR(INDEX('03 Raw Data'!$Q$3:$Q$722,MATCH($A11,'03 Raw Data'!$P$3:$P$722,0)),"")) | H11: =IF($A11="","",IFERROR(INDEX('03 Raw Data'!$T$3:$T$722,MATCH($A11,'03 Raw Data'!$S$3:$S$722,0)),""))
A12: =IFERROR(IF(OR('03 Raw Data'!A10="",'03 Raw Data'!A10=0),"",'03 Raw Data'!A10),"") | B12: =IF($A12="","",IFERROR(INDEX('03 Raw Data'!$B$3:$B$722,MATCH($A12,'03 Raw Data'!$A$3:$A$722,0)),"")) | C12: =IF($A12="","",IFERROR(INDEX('03 Raw Data'!$E$3:$E$722,MATCH($A12,'03 Raw Data'!$D$3:$D$722,0)),"")) | D12: =IF($A12="","",IFERROR(INDEX('03 Raw Data'!$H$3:$H$722,MATCH($A12,'03 Raw Data'!$G$3:$G$722,0)),"")) | E12: =IF($A12="","",IFERROR(INDEX('03 Raw Data'!$K$3:$K$722,MATCH($A12,'03 Raw Data'!$J$3:$J$722,0)),"")) | F12: =IF($A12="","",IFERROR(INDEX('03 Raw Data'!$N$3:$N$722,MATCH($A12,'03 Raw Data'!$M$3:$M$722,0)),"")) | G12: =IF($A12="","",IFERROR(INDEX('03 Raw Data'!$Q$3:$Q$722,MATCH($A12,'03 Raw Data'!$P$3:$P$722,0)),"")) | H12: =IF($A12="","",IFERROR(INDEX('03 Raw Data'!$T$3:$T$722,MATCH($A12,'03 Raw Data'!$S$3:$S$722,0)),""))
A13: =IFERROR(IF(OR('03 Raw Data'!A11="",'03 Raw Data'!A11=0),"",'03 Raw Data'!A11),"") | B13: =IF($A13="","",IFERROR(INDEX('03 Raw Data'!$B$3:$B$722,MATCH($A13,'03 Raw Data'!$A$3:$A$722,0)),"")) | C13: =IF($A13="","",IFERROR(INDEX('03 Raw Data'!$E$3:$E$722,MATCH($A13,'03 Raw Data'!$D$3:$D$722,0)),"")) | D13: =IF($A13="","",IFERROR(INDEX('03 Raw Data'!$H$3:$H$722,MATCH($A13,'03 Raw Data'!$G$3:$G$722,0)),"")) | E13: =IF($A13="","",IFERROR(INDEX('03 Raw Data'!$K$3:$K$722,MATCH($A13,'03 Raw Data'!$J$3:$J$722,0)),"")) | F13: =IF($A13="","",IFERROR(INDEX('03 Raw Data'!$N$3:$N$722,MATCH($A13,'03 Raw Data'!$M$3:$M$722,0)),"")) | G13: =IF($A13="","",IFERROR(INDEX('03 Raw Data'!$Q$3:$Q$722,MATCH($A13,'03 Raw Data'!$P$3:$P$722,0)),"")) | H13: =IF($A13="","",IFERROR(INDEX('03 Raw Data'!$T$3:$T$722,MATCH($A13,'03 Raw Data'!$S$3:$S$722,0)),""))
A14: =IFERROR(IF(OR('03 Raw Data'!A12="",'03 Raw Data'!A12=0),"",'03 Raw Data'!A12),"") | B14: =IF($A14="","",IFERROR(INDEX('03 Raw Data'!$B$3:$B$722,MATCH($A14,'03 Raw Data'!$A$3:$A$722,0)),"")) | C14: =IF($A14="","",IFERROR(INDEX('03 Raw Data'!$E$3:$E$722,MATCH($A14,'03 Raw Data'!$D$3:$D$722,0)),"")) | D14: =IF($A14="","",IFERROR(INDEX('03 Raw Data'!$H$3:$H$722,MATCH($A14,'03 Raw Data'!$G$3:$G$722,0)),"")) | E14: =IF($A14="","",IFERROR(INDEX('03 Raw Data'!$K$3:$K$722,MATCH($A14,'03 Raw Data'!$J$3:$J$722,0)),"")) | F14: =IF($A14="","",IFERROR(INDEX('03 Raw Data'!$N$3:$N$722,MATCH($A14,'03 Raw Data'!$M$3:$M$722,0)),"")) | G14: =IF($A14="","",IFERROR(INDEX('03 Raw Data'!$Q$3:$Q$722,MATCH($A14,'03 Raw Data'!$P$3:$P$722,0)),"")) | H14: =IF($A14="","",IFERROR(INDEX('03 Raw Data'!$T$3:$T$722,MATCH($A14,'03 Raw Data'!$S$3:$S$722,0)),""))
A15: =IFERROR(IF(OR('03 Raw Data'!A13="",'03 Raw Data'!A13=0),"",'03 Raw Data'!A13),"") | B15: =IF($A15="","",IFERROR(INDEX('03 Raw Data'!$B$3:$B$722,MATCH($A15,'03 Raw Data'!$A$3:$A$722,0)),"")) | C15: =IF($A15="","",IFERROR(INDEX('03 Raw Data'!$E$3:$E$722,MATCH($A15,'03 Raw Data'!$D$3:$D$722,0)),"")) | D15: =IF($A15="","",IFERROR(INDEX('03 Raw Data'!$H$3:$H$722,MATCH($A15,'03 Raw Data'!$G$3:$G$722,0)),"")) | E15: =IF($A15="","",IFERROR(INDEX('03 Raw Data'!$K$3:$K$722,MATCH($A15,'03 Raw Data'!$J$3:$J$722,0)),"")) | F15: =IF($A15="","",IFERROR(INDEX('03 Raw Data'!$N$3:$N$722,MATCH($A15,'03 Raw Data'!$M$3:$M$722,0)),"")) | G15: =IF($A15="","",IFERROR(INDEX('03 Raw Data'!$Q$3:$Q$722,MATCH($A15,'03 Raw Data'!$P$3:$P$722,0)),"")) | H15: =IF($A15="","",IFERROR(INDEX('03 Raw Data'!$T$3:$T$722,MATCH($A15,'03 Raw Data'!$S$3:$S$722,0)),""))
A16: =IFERROR(IF(OR('03 Raw Data'!A14="",'03 Raw Data'!A14=0),"",'03 Raw Data'!A14),"") | B16: =IF($A16="","",IFERROR(INDEX('03 Raw Data'!$B$3:$B$722,MATCH($A16,'03 Raw Data'!$A$3:$A$722,0)),"")) | C16: =IF($A16="","",IFERROR(INDEX('03 Raw Data'!$E$3:$E$722,MATCH($A16,'03 Raw Data'!$D$3:$D$722,0)),"")) | D16: =IF($A16="","",IFERROR(INDEX('03 Raw Data'!$H$3:$H$722,MATCH($A16,'03 Raw Data'!$G$3:$G$722,0)),"")) | E16: =IF($A16="","",IFERROR(INDEX('03 Raw Data'!$K$3:$K$722,MATCH($A16,'03 Raw Data'!$J$3:$J$722,0)),"")) | F16: =IF($A16="","",IFERROR(INDEX('03 Raw Data'!$N$3:$N$722,MATCH($A16,'03 Raw Data'!$M$3:$M$722,0)),"")) | G16: =IF($A16="","",IFERROR(INDEX('03 Raw Data'!$Q$3:$Q$722,MATCH($A16,'03 Raw Data'!$P$3:$P$722,0)),"")) | H16: =IF($A16="","",IFERROR(INDEX('03 Raw Data'!$T$3:$T$722,MATCH($A16,'03 Raw Data'!$S$3:$S$722,0)),""))
... A724: =IFERROR(IF(OR('03 Raw Data'!A722="",'03 Raw Data'!A722=0),"",'03 Raw Data'!A722),"") | B724: =IF($A724="","",IFERROR(INDEX('03 Raw Data'!$B$3:$B$722,MATCH($A724,'03 Raw Data'!$A$3:$A$722,0)),"")) | C724: =IF($A724="","",IFERROR(INDEX('03 Raw Data'!$E$3:$E$722,MATCH($A724,'03 Raw Data'!$D$3:$D$722,0)),"")) | D724: =IF($A724="","",IFERROR(INDEX('03 Raw Data'!$H$3:$H$722,MATCH($A724,'03 Raw Data'!$G$3:$G$722,0)),"")) | E724: =IF($A724="","",IFERROR(INDEX('03 Raw Data'!$K$3:$K$722,MATCH($A724,'03 Raw Data'!$J$3:$J$722,0)),"")) | F724: =IF($A724="","",IFERROR(INDEX('03 Raw Data'!$N$3:$N$722,MATCH($A724,'03 Raw Data'!$M$3:$M$722,0)),"")) | G724: =IF($A724="","",IFERROR(INDEX('03 Raw Data'!$Q$3:$Q$722,MATCH($A724,'03 Raw Data'!$P$3:$P$722,0)),"")) | H724: =IF($A724="","",IFERROR(INDEX('03 Raw Data'!$T$3:$T$722,MATCH($A724,'03 Raw Data'!$S$3:$S$722,0)),""))

Sheet 05 Simple Returns
A1: Daily Simple (Arithmetic) Returns
A2: r_t = P_t / P_(t-1) - 1, one row per trading day after the first. Simple returns aggregate correctly ACROSS ASSETS, which is why the portfolio return series and every risk metric are built from these.
A3: Mirrors: returns.py -> simple_returns(prices) = prices.pct_change().dropna()
A4: Date | B4: JPM | C4: MS | D4: BAC | E4: AAPL | F4: MSFT | G4: GLD | H4: BENCHMARK
A5: =IF('04 Prices'!A6="","",'04 Prices'!A6) | B5: =IF(OR($A5="",'04 Prices'!B5="",'04 Prices'!B6=""),"",'04 Prices'!B6/'04 Prices'!B5-1) | C5: =IF(OR($A5="",'04 Prices'!C5="",'04 Prices'!C6=""),"",'04 Prices'!C6/'04 Prices'!C5-1) | D5: =IF(OR($A5="",'04 Prices'!D5="",'04 Prices'!D6=""),"",'04 Prices'!D6/'04 Prices'!D5-1) | E5: =IF(OR($A5="",'04 Prices'!E5="",'04 Prices'!E6=""),"",'04 Prices'!E6/'04 Prices'!E5-1) | F5: =IF(OR($A5="",'04 Prices'!F5="",'04 Prices'!F6=""),"",'04 Prices'!F6/'04 Prices'!F5-1) | G5: =IF(OR($A5="",'04 Prices'!G5="",'04 Prices'!G6=""),"",'04 Prices'!G6/'04 Prices'!G5-1) | H5: =IF(OR($A5="",'04 Prices'!H5="",'04 Prices'!H6=""),"",'04 Prices'!H6/'04 Prices'!H5-1)
A6: =IF('04 Prices'!A7="","",'04 Prices'!A7) | B6: =IF(OR($A6="",'04 Prices'!B6="",'04 Prices'!B7=""),"",'04 Prices'!B7/'04 Prices'!B6-1) | C6: =IF(OR($A6="",'04 Prices'!C6="",'04 Prices'!C7=""),"",'04 Prices'!C7/'04 Prices'!C6-1) | D6: =IF(OR($A6="",'04 Prices'!D6="",'04 Prices'!D7=""),"",'04 Prices'!D7/'04 Prices'!D6-1) | E6: =IF(OR($A6="",'04 Prices'!E6="",'04 Prices'!E7=""),"",'04 Prices'!E7/'04 Prices'!E6-1) | F6: =IF(OR($A6="",'04 Prices'!F6="",'04 Prices'!F7=""),"",'04 Prices'!F7/'04 Prices'!F6-1) | G6: =IF(OR($A6="",'04 Prices'!G6="",'04 Prices'!G7=""),"",'04 Prices'!G7/'04 Prices'!G6-1) | H6: =IF(OR($A6="",'04 Prices'!H6="",'04 Prices'!H7=""),"",'04 Prices'!H7/'04 Prices'!H6-1)
A7: =IF('04 Prices'!A8="","",'04 Prices'!A8) | B7: =IF(OR($A7="",'04 Prices'!B7="",'04 Prices'!B8=""),"",'04 Prices'!B8/'04 Prices'!B7-1) | C7: =IF(OR($A7="",'04 Prices'!C7="",'04 Prices'!C8=""),"",'04 Prices'!C8/'04 Prices'!C7-1) | D7: =IF(OR($A7="",'04 Prices'!D7="",'04 Prices'!D8=""),"",'04 Prices'!D8/'04 Prices'!D7-1) | E7: =IF(OR($A7="",'04 Prices'!E7="",'04 Prices'!E8=""),"",'04 Prices'!E8/'04 Prices'!E7-1) | F7: =IF(OR($A7="",'04 Prices'!F7="",'04 Prices'!F8=""),"",'04 Prices'!F8/'04 Prices'!F7-1) | G7: =IF(OR($A7="",'04 Prices'!G7="",'04 Prices'!G8=""),"",'04 Prices'!G8/'04 Prices'!G7-1) | H7: =IF(OR($A7="",'04 Prices'!H7="",'04 Prices'!H8=""),"",'04 Prices'!H8/'04 Prices'!H7-1)
A8: =IF('04 Prices'!A9="","",'04 Prices'!A9) | B8: =IF(OR($A8="",'04 Prices'!B8="",'04 Prices'!B9=""),"",'04 Prices'!B9/'04 Prices'!B8-1) | C8: =IF(OR($A8="",'04 Prices'!C8="",'04 Prices'!C9=""),"",'04 Prices'!C9/'04 Prices'!C8-1) | D8: =IF(OR($A8="",'04 Prices'!D8="",'04 Prices'!D9=""),"",'04 Prices'!D9/'04 Prices'!D8-1) | E8: =IF(OR($A8="",'04 Prices'!E8="",'04 Prices'!E9=""),"",'04 Prices'!E9/'04 Prices'!E8-1) | F8: =IF(OR($A8="",'04 Prices'!F8="",'04 Prices'!F9=""),"",'04 Prices'!F9/'04 Prices'!F8-1) | G8: =IF(OR($A8="",'04 Prices'!G8="",'04 Prices'!G9=""),"",'04 Prices'!G9/'04 Prices'!G8-1) | H8: =IF(OR($A8="",'04 Prices'!H8="",'04 Prices'!H9=""),"",'04 Prices'!H9/'04 Prices'!H8-1)
A9: =IF('04 Prices'!A10="","",'04 Prices'!A10) | B9: =IF(OR($A9="",'04 Prices'!B9="",'04 Prices'!B10=""),"",'04 Prices'!B10/'04 Prices'!B9-1) | C9: =IF(OR($A9="",'04 Prices'!C9="",'04 Prices'!C10=""),"",'04 Prices'!C10/'04 Prices'!C9-1) | D9: =IF(OR($A9="",'04 Prices'!D9="",'04 Prices'!D10=""),"",'04 Prices'!D10/'04 Prices'!D9-1) | E9: =IF(OR($A9="",'04 Prices'!E9="",'04 Prices'!E10=""),"",'04 Prices'!E10/'04 Prices'!E9-1) | F9: =IF(OR($A9="",'04 Prices'!F9="",'04 Prices'!F10=""),"",'04 Prices'!F10/'04 Prices'!F9-1) | G9: =IF(OR($A9="",'04 Prices'!G9="",'04 Prices'!G10=""),"",'04 Prices'!G10/'04 Prices'!G9-1) | H9: =IF(OR($A9="",'04 Prices'!H9="",'04 Prices'!H10=""),"",'04 Prices'!H10/'04 Prices'!H9-1)
A10: =IF('04 Prices'!A11="","",'04 Prices'!A11) | B10: =IF(OR($A10="",'04 Prices'!B10="",'04 Prices'!B11=""),"",'04 Prices'!B11/'04 Prices'!B10-1) | C10: =IF(OR($A10="",'04 Prices'!C10="",'04 Prices'!C11=""),"",'04 Prices'!C11/'04 Prices'!C10-1) | D10: =IF(OR($A10="",'04 Prices'!D10="",'04 Prices'!D11=""),"",'04 Prices'!D11/'04 Prices'!D10-1) | E10: =IF(OR($A10="",'04 Prices'!E10="",'04 Prices'!E11=""),"",'04 Prices'!E11/'04 Prices'!E10-1) | F10: =IF(OR($A10="",'04 Prices'!F10="",'04 Prices'!F11=""),"",'04 Prices'!F11/'04 Prices'!F10-1) | G10: =IF(OR($A10="",'04 Prices'!G10="",'04 Prices'!G11=""),"",'04 Prices'!G11/'04 Prices'!G10-1) | H10: =IF(OR($A10="",'04 Prices'!H10="",'04 Prices'!H11=""),"",'04 Prices'!H11/'04 Prices'!H10-1)
A11: =IF('04 Prices'!A12="","",'04 Prices'!A12) | B11: =IF(OR($A11="",'04 Prices'!B11="",'04 Prices'!B12=""),"",'04 Prices'!B12/'04 Prices'!B11-1) | C11: =IF(OR($A11="",'04 Prices'!C11="",'04 Prices'!C12=""),"",'04 Prices'!C12/'04 Prices'!C11-1) | D11: =IF(OR($A11="",'04 Prices'!D11="",'04 Prices'!D12=""),"",'04 Prices'!D12/'04 Prices'!D11-1) | E11: =IF(OR($A11="",'04 Prices'!E11="",'04 Prices'!E12=""),"",'04 Prices'!E12/'04 Prices'!E11-1) | F11: =IF(OR($A11="",'04 Prices'!F11="",'04 Prices'!F12=""),"",'04 Prices'!F12/'04 Prices'!F11-1) | G11: =IF(OR($A11="",'04 Prices'!G11="",'04 Prices'!G12=""),"",'04 Prices'!G12/'04 Prices'!G11-1) | H11: =IF(OR($A11="",'04 Prices'!H11="",'04 Prices'!H12=""),"",'04 Prices'!H12/'04 Prices'!H11-1)
A12: =IF('04 Prices'!A13="","",'04 Prices'!A13) | B12: =IF(OR($A12="",'04 Prices'!B12="",'04 Prices'!B13=""),"",'04 Prices'!B13/'04 Prices'!B12-1) | C12: =IF(OR($A12="",'04 Prices'!C12="",'04 Prices'!C13=""),"",'04 Prices'!C13/'04 Prices'!C12-1) | D12: =IF(OR($A12="",'04 Prices'!D12="",'04 Prices'!D13=""),"",'04 Prices'!D13/'04 Prices'!D12-1) | E12: =IF(OR($A12="",'04 Prices'!E12="",'04 Prices'!E13=""),"",'04 Prices'!E13/'04 Prices'!E12-1) | F12: =IF(OR($A12="",'04 Prices'!F12="",'04 Prices'!F13=""),"",'04 Prices'!F13/'04 Prices'!F12-1) | G12: =IF(OR($A12="",'04 Prices'!G12="",'04 Prices'!G13=""),"",'04 Prices'!G13/'04 Prices'!G12-1) | H12: =IF(OR($A12="",'04 Prices'!H12="",'04 Prices'!H13=""),"",'04 Prices'!H13/'04 Prices'!H12-1)
A13: =IF('04 Prices'!A14="","",'04 Prices'!A14) | B13: =IF(OR($A13="",'04 Prices'!B13="",'04 Prices'!B14=""),"",'04 Prices'!B14/'04 Prices'!B13-1) | C13: =IF(OR($A13="",'04 Prices'!C13="",'04 Prices'!C14=""),"",'04 Prices'!C14/'04 Prices'!C13-1) | D13: =IF(OR($A13="",'04 Prices'!D13="",'04 Prices'!D14=""),"",'04 Prices'!D14/'04 Prices'!D13-1) | E13: =IF(OR($A13="",'04 Prices'!E13="",'04 Prices'!E14=""),"",'04 Prices'!E14/'04 Prices'!E13-1) | F13: =IF(OR($A13="",'04 Prices'!F13="",'04 Prices'!F14=""),"",'04 Prices'!F14/'04 Prices'!F13-1) | G13: =IF(OR($A13="",'04 Prices'!G13="",'04 Prices'!G14=""),"",'04 Prices'!G14/'04 Prices'!G13-1) | H13: =IF(OR($A13="",'04 Prices'!H13="",'04 Prices'!H14=""),"",'04 Prices'!H14/'04 Prices'!H13-1)
A14: =IF('04 Prices'!A15="","",'04 Prices'!A15) | B14: =IF(OR($A14="",'04 Prices'!B14="",'04 Prices'!B15=""),"",'04 Prices'!B15/'04 Prices'!B14-1) | C14: =IF(OR($A14="",'04 Prices'!C14="",'04 Prices'!C15=""),"",'04 Prices'!C15/'04 Prices'!C14-1) | D14: =IF(OR($A14="",'04 Prices'!D14="",'04 Prices'!D15=""),"",'04 Prices'!D15/'04 Prices'!D14-1) | E14: =IF(OR($A14="",'04 Prices'!E14="",'04 Prices'!E15=""),"",'04 Prices'!E15/'04 Prices'!E14-1) | F14: =IF(OR($A14="",'04 Prices'!F14="",'04 Prices'!F15=""),"",'04 Prices'!F15/'04 Prices'!F14-1) | G14: =IF(OR($A14="",'04 Prices'!G14="",'04 Prices'!G15=""),"",'04 Prices'!G15/'04 Prices'!G14-1) | H14: =IF(OR($A14="",'04 Prices'!H14="",'04 Prices'!H15=""),"",'04 Prices'!H15/'04 Prices'!H14-1)
A15: =IF('04 Prices'!A16="","",'04 Prices'!A16) | B15: =IF(OR($A15="",'04 Prices'!B15="",'04 Prices'!B16=""),"",'04 Prices'!B16/'04 Prices'!B15-1) | C15: =IF(OR($A15="",'04 Prices'!C15="",'04 Prices'!C16=""),"",'04 Prices'!C16/'04 Prices'!C15-1) | D15: =IF(OR($A15="",'04 Prices'!D15="",'04 Prices'!D16=""),"",'04 Prices'!D16/'04 Prices'!D15-1) | E15: =IF(OR($A15="",'04 Prices'!E15="",'04 Prices'!E16=""),"",'04 Prices'!E16/'04 Prices'!E15-1) | F15: =IF(OR($A15="",'04 Prices'!F15="",'04 Prices'!F16=""),"",'04 Prices'!F16/'04 Prices'!F15-1) | G15: =IF(OR($A15="",'04 Prices'!G15="",'04 Prices'!G16=""),"",'04 Prices'!G16/'04 Prices'!G15-1) | H15: =IF(OR($A15="",'04 Prices'!H15="",'04 Prices'!H16=""),"",'04 Prices'!H16/'04 Prices'!H15-1)
A16: =IF('04 Prices'!A17="","",'04 Prices'!A17) | B16: =IF(OR($A16="",'04 Prices'!B16="",'04 Prices'!B17=""),"",'04 Prices'!B17/'04 Prices'!B16-1) | C16: =IF(OR($A16="",'04 Prices'!C16="",'04 Prices'!C17=""),"",'04 Prices'!C17/'04 Prices'!C16-1) | D16: =IF(OR($A16="",'04 Prices'!D16="",'04 Prices'!D17=""),"",'04 Prices'!D17/'04 Prices'!D16-1) | E16: =IF(OR($A16="",'04 Prices'!E16="",'04 Prices'!E17=""),"",'04 Prices'!E17/'04 Prices'!E16-1) | F16: =IF(OR($A16="",'04 Prices'!F16="",'04 Prices'!F17=""),"",'04 Prices'!F17/'04 Prices'!F16-1) | G16: =IF(OR($A16="",'04 Prices'!G16="",'04 Prices'!G17=""),"",'04 Prices'!G17/'04 Prices'!G16-1) | H16: =IF(OR($A16="",'04 Prices'!H16="",'04 Prices'!H17=""),"",'04 Prices'!H17/'04 Prices'!H16-1)
... A723: =IF('04 Prices'!A724="","",'04 Prices'!A724) | B723: =IF(OR($A723="",'04 Prices'!B723="",'04 Prices'!B724=""),"",'04 Prices'!B724/'04 Prices'!B723-1) | C723: =IF(OR($A723="",'04 Prices'!C723="",'04 Prices'!C724=""),"",'04 Prices'!C724/'04 Prices'!C723-1) | D723: =IF(OR($A723="",'04 Prices'!D723="",'04 Prices'!D724=""),"",'04 Prices'!D724/'04 Prices'!D723-1) | E723: =IF(OR($A723="",'04 Prices'!E723="",'04 Prices'!E724=""),"",'04 Prices'!E724/'04 Prices'!E723-1) | F723: =IF(OR($A723="",'04 Prices'!F723="",'04 Prices'!F724=""),"",'04 Prices'!F724/'04 Prices'!F723-1) | G723: =IF(OR($A723="",'04 Prices'!G723="",'04 Prices'!G724=""),"",'04 Prices'!G724/'04 Prices'!G723-1) | H723: =IF(OR($A723="",'04 Prices'!H723="",'04 Prices'!H724=""),"",'04 Prices'!H724/'04 Prices'!H723-1)

Sheet 06 Log Returns
A1: Daily Logarithmic (Continuously Compounded) Returns
A2: r_t = ln(P_t / P_(t-1)). Log returns add up ACROSS TIME, which makes them the right input for annualising and for the covariance matrix that drives the Markowitz optimisation.
A3: Mirrors: returns.py -> log_returns(prices) = np.log(prices / prices.shift(1)).dropna()
A4: Date | B4: JPM | C4: MS | D4: BAC | E4: AAPL | F4: MSFT | G4: GLD | H4: BENCHMARK
A5: =IF('04 Prices'!A6="","",'04 Prices'!A6) | B5: =IF(OR($A5="",'04 Prices'!B5="",'04 Prices'!B6=""),"",LN('04 Prices'!B6/'04 Prices'!B5)) | C5: =IF(OR($A5="",'04 Prices'!C5="",'04 Prices'!C6=""),"",LN('04 Prices'!C6/'04 Prices'!C5)) | D5: =IF(OR($A5="",'04 Prices'!D5="",'04 Prices'!D6=""),"",LN('04 Prices'!D6/'04 Prices'!D5)) | E5: =IF(OR($A5="",'04 Prices'!E5="",'04 Prices'!E6=""),"",LN('04 Prices'!E6/'04 Prices'!E5)) | F5: =IF(OR($A5="",'04 Prices'!F5="",'04 Prices'!F6=""),"",LN('04 Prices'!F6/'04 Prices'!F5)) | G5: =IF(OR($A5="",'04 Prices'!G5="",'04 Prices'!G6=""),"",LN('04 Prices'!G6/'04 Prices'!G5)) | H5: =IF(OR($A5="",'04 Prices'!H5="",'04 Prices'!H6=""),"",LN('04 Prices'!H6/'04 Prices'!H5))
A6: =IF('04 Prices'!A7="","",'04 Prices'!A7) | B6: =IF(OR($A6="",'04 Prices'!B6="",'04 Prices'!B7=""),"",LN('04 Prices'!B7/'04 Prices'!B6)) | C6: =IF(OR($A6="",'04 Prices'!C6="",'04 Prices'!C7=""),"",LN('04 Prices'!C7/'04 Prices'!C6)) | D6: =IF(OR($A6="",'04 Prices'!D6="",'04 Prices'!D7=""),"",LN('04 Prices'!D7/'04 Prices'!D6)) | E6: =IF(OR($A6="",'04 Prices'!E6="",'04 Prices'!E7=""),"",LN('04 Prices'!E7/'04 Prices'!E6)) | F6: =IF(OR($A6="",'04 Prices'!F6="",'04 Prices'!F7=""),"",LN('04 Prices'!F7/'04 Prices'!F6)) | G6: =IF(OR($A6="",'04 Prices'!G6="",'04 Prices'!G7=""),"",LN('04 Prices'!G7/'04 Prices'!G6)) | H6: =IF(OR($A6="",'04 Prices'!H6="",'04 Prices'!H7=""),"",LN('04 Prices'!H7/'04 Prices'!H6))
A7: =IF('04 Prices'!A8="","",'04 Prices'!A8) | B7: =IF(OR($A7="",'04 Prices'!B7="",'04 Prices'!B8=""),"",LN('04 Prices'!B8/'04 Prices'!B7)) | C7: =IF(OR($A7="",'04 Prices'!C7="",'04 Prices'!C8=""),"",LN('04 Prices'!C8/'04 Prices'!C7)) | D7: =IF(OR($A7="",'04 Prices'!D7="",'04 Prices'!D8=""),"",LN('04 Prices'!D8/'04 Prices'!D7)) | E7: =IF(OR($A7="",'04 Prices'!E7="",'04 Prices'!E8=""),"",LN('04 Prices'!E8/'04 Prices'!E7)) | F7: =IF(OR($A7="",'04 Prices'!F7="",'04 Prices'!F8=""),"",LN('04 Prices'!F8/'04 Prices'!F7)) | G7: =IF(OR($A7="",'04 Prices'!G7="",'04 Prices'!G8=""),"",LN('04 Prices'!G8/'04 Prices'!G7)) | H7: =IF(OR($A7="",'04 Prices'!H7="",'04 Prices'!H8=""),"",LN('04 Prices'!H8/'04 Prices'!H7))
A8: =IF('04 Prices'!A9="","",'04 Prices'!A9) | B8: =IF(OR($A8="",'04 Prices'!B8="",'04 Prices'!B9=""),"",LN('04 Prices'!B9/'04 Prices'!B8)) | C8: =IF(OR($A8="",'04 Prices'!C8="",'04 Prices'!C9=""),"",LN('04 Prices'!C9/'04 Prices'!C8)) | D8: =IF(OR($A8="",'04 Prices'!D8="",'04 Prices'!D9=""),"",LN('04 Prices'!D9/'04 Prices'!D8)) | E8: =IF(OR($A8="",'04 Prices'!E8="",'04 Prices'!E9=""),"",LN('04 Prices'!E9/'04 Prices'!E8)) | F8: =IF(OR($A8="",'04 Prices'!F8="",'04 Prices'!F9=""),"",LN('04 Prices'!F9/'04 Prices'!F8)) | G8: =IF(OR($A8="",'04 Prices'!G8="",'04 Prices'!G9=""),"",LN('04 Prices'!G9/'04 Prices'!G8)) | H8: =IF(OR($A8="",'04 Prices'!H8="",'04 Prices'!H9=""),"",LN('04 Prices'!H9/'04 Prices'!H8))
A9: =IF('04 Prices'!A10="","",'04 Prices'!A10) | B9: =IF(OR($A9="",'04 Prices'!B9="",'04 Prices'!B10=""),"",LN('04 Prices'!B10/'04 Prices'!B9)) | C9: =IF(OR($A9="",'04 Prices'!C9="",'04 Prices'!C10=""),"",LN('04 Prices'!C10/'04 Prices'!C9)) | D9: =IF(OR($A9="",'04 Prices'!D9="",'04 Prices'!D10=""),"",LN('04 Prices'!D10/'04 Prices'!D9)) | E9: =IF(OR($A9="",'04 Prices'!E9="",'04 Prices'!E10=""),"",LN('04 Prices'!E10/'04 Prices'!E9)) | F9: =IF(OR($A9="",'04 Prices'!F9="",'04 Prices'!F10=""),"",LN('04 Prices'!F10/'04 Prices'!F9)) | G9: =IF(OR($A9="",'04 Prices'!G9="",'04 Prices'!G10=""),"",LN('04 Prices'!G10/'04 Prices'!G9)) | H9: =IF(OR($A9="",'04 Prices'!H9="",'04 Prices'!H10=""),"",LN('04 Prices'!H10/'04 Prices'!H9))
A10: =IF('04 Prices'!A11="","",'04 Prices'!A11) | B10: =IF(OR($A10="",'04 Prices'!B10="",'04 Prices'!B11=""),"",LN('04 Prices'!B11/'04 Prices'!B10)) | C10: =IF(OR($A10="",'04 Prices'!C10="",'04 Prices'!C11=""),"",LN('04 Prices'!C11/'04 Prices'!C10)) | D10: =IF(OR($A10="",'04 Prices'!D10="",'04 Prices'!D11=""),"",LN('04 Prices'!D11/'04 Prices'!D10)) | E10: =IF(OR($A10="",'04 Prices'!E10="",'04 Prices'!E11=""),"",LN('04 Prices'!E11/'04 Prices'!E10)) | F10: =IF(OR($A10="",'04 Prices'!F10="",'04 Prices'!F11=""),"",LN('04 Prices'!F11/'04 Prices'!F10)) | G10: =IF(OR($A10="",'04 Prices'!G10="",'04 Prices'!G11=""),"",LN('04 Prices'!G11/'04 Prices'!G10)) | H10: =IF(OR($A10="",'04 Prices'!H10="",'04 Prices'!H11=""),"",LN('04 Prices'!H11/'04 Prices'!H10))
A11: =IF('04 Prices'!A12="","",'04 Prices'!A12) | B11: =IF(OR($A11="",'04 Prices'!B11="",'04 Prices'!B12=""),"",LN('04 Prices'!B12/'04 Prices'!B11)) | C11: =IF(OR($A11="",'04 Prices'!C11="",'04 Prices'!C12=""),"",LN('04 Prices'!C12/'04 Prices'!C11)) | D11: =IF(OR($A11="",'04 Prices'!D11="",'04 Prices'!D12=""),"",LN('04 Prices'!D12/'04 Prices'!D11)) | E11: =IF(OR($A11="",'04 Prices'!E11="",'04 Prices'!E12=""),"",LN('04 Prices'!E12/'04 Prices'!E11)) | F11: =IF(OR($A11="",'04 Prices'!F11="",'04 Prices'!F12=""),"",LN('04 Prices'!F12/'04 Prices'!F11)) | G11: =IF(OR($A11="",'04 Prices'!G11="",'04 Prices'!G12=""),"",LN('04 Prices'!G12/'04 Prices'!G11)) | H11: =IF(OR($A11="",'04 Prices'!H11="",'04 Prices'!H12=""),"",LN('04 Prices'!H12/'04 Prices'!H11))
A12: =IF('04 Prices'!A13="","",'04 Prices'!A13) | B12: =IF(OR($A12="",'04 Prices'!B12="",'04 Prices'!B13=""),"",LN('04 Prices'!B13/'04 Prices'!B12)) | C12: =IF(OR($A12="",'04 Prices'!C12="",'04 Prices'!C13=""),"",LN('04 Prices'!C13/'04 Prices'!C12)) | D12: =IF(OR($A12="",'04 Prices'!D12="",'04 Prices'!D13=""),"",LN('04 Prices'!D13/'04 Prices'!D12)) | E12: =IF(OR($A12="",'04 Prices'!E12="",'04 Prices'!E13=""),"",LN('04 Prices'!E13/'04 Prices'!E12)) | F12: =IF(OR($A12="",'04 Prices'!F12="",'04 Prices'!F13=""),"",LN('04 Prices'!F13/'04 Prices'!F12)) | G12: =IF(OR($A12="",'04 Prices'!G12="",'04 Prices'!G13=""),"",LN('04 Prices'!G13/'04 Prices'!G12)) | H12: =IF(OR($A12="",'04 Prices'!H12="",'04 Prices'!H13=""),"",LN('04 Prices'!H13/'04 Prices'!H12))
A13: =IF('04 Prices'!A14="","",'04 Prices'!A14) | B13: =IF(OR($A13="",'04 Prices'!B13="",'04 Prices'!B14=""),"",LN('04 Prices'!B14/'04 Prices'!B13)) | C13: =IF(OR($A13="",'04 Prices'!C13="",'04 Prices'!C14=""),"",LN('04 Prices'!C14/'04 Prices'!C13)) | D13: =IF(OR($A13="",'04 Prices'!D13="",'04 Prices'!D14=""),"",LN('04 Prices'!D14/'04 Prices'!D13)) | E13: =IF(OR($A13="",'04 Prices'!E13="",'04 Prices'!E14=""),"",LN('04 Prices'!E14/'04 Prices'!E13)) | F13: =IF(OR($A13="",'04 Prices'!F13="",'04 Prices'!F14=""),"",LN('04 Prices'!F14/'04 Prices'!F13)) | G13: =IF(OR($A13="",'04 Prices'!G13="",'04 Prices'!G14=""),"",LN('04 Prices'!G14/'04 Prices'!G13)) | H13: =IF(OR($A13="",'04 Prices'!H13="",'04 Prices'!H14=""),"",LN('04 Prices'!H14/'04 Prices'!H13))
A14: =IF('04 Prices'!A15="","",'04 Prices'!A15) | B14: =IF(OR($A14="",'04 Prices'!B14="",'04 Prices'!B15=""),"",LN('04 Prices'!B15/'04 Prices'!B14)) | C14: =IF(OR($A14="",'04 Prices'!C14="",'04 Prices'!C15=""),"",LN('04 Prices'!C15/'04 Prices'!C14)) | D14: =IF(OR($A14="",'04 Prices'!D14="",'04 Prices'!D15=""),"",LN('04 Prices'!D15/'04 Prices'!D14)) | E14: =IF(OR($A14="",'04 Prices'!E14="",'04 Prices'!E15=""),"",LN('04 Prices'!E15/'04 Prices'!E14)) | F14: =IF(OR($A14="",'04 Prices'!F14="",'04 Prices'!F15=""),"",LN('04 Prices'!F15/'04 Prices'!F14)) | G14: =IF(OR($A14="",'04 Prices'!G14="",'04 Prices'!G15=""),"",LN('04 Prices'!G15/'04 Prices'!G14)) | H14: =IF(OR($A14="",'04 Prices'!H14="",'04 Prices'!H15=""),"",LN('04 Prices'!H15/'04 Prices'!H14))
A15: =IF('04 Prices'!A16="","",'04 Prices'!A16) | B15: =IF(OR($A15="",'04 Prices'!B15="",'04 Prices'!B16=""),"",LN('04 Prices'!B16/'04 Prices'!B15)) | C15: =IF(OR($A15="",'04 Prices'!C15="",'04 Prices'!C16=""),"",LN('04 Prices'!C16/'04 Prices'!C15)) | D15: =IF(OR($A15="",'04 Prices'!D15="",'04 Prices'!D16=""),"",LN('04 Prices'!D16/'04 Prices'!D15)) | E15: =IF(OR($A15="",'04 Prices'!E15="",'04 Prices'!E16=""),"",LN('04 Prices'!E16/'04 Prices'!E15)) | F15: =IF(OR($A15="",'04 Prices'!F15="",'04 Prices'!F16=""),"",LN('04 Prices'!F16/'04 Prices'!F15)) | G15: =IF(OR($A15="",'04 Prices'!G15="",'04 Prices'!G16=""),"",LN('04 Prices'!G16/'04 Prices'!G15)) | H15: =IF(OR($A15="",'04 Prices'!H15="",'04 Prices'!H16=""),"",LN('04 Prices'!H16/'04 Prices'!H15))
A16: =IF('04 Prices'!A17="","",'04 Prices'!A17) | B16: =IF(OR($A16="",'04 Prices'!B16="",'04 Prices'!B17=""),"",LN('04 Prices'!B17/'04 Prices'!B16)) | C16: =IF(OR($A16="",'04 Prices'!C16="",'04 Prices'!C17=""),"",LN('04 Prices'!C17/'04 Prices'!C16)) | D16: =IF(OR($A16="",'04 Prices'!D16="",'04 Prices'!D17=""),"",LN('04 Prices'!D17/'04 Prices'!D16)) | E16: =IF(OR($A16="",'04 Prices'!E16="",'04 Prices'!E17=""),"",LN('04 Prices'!E17/'04 Prices'!E16)) | F16: =IF(OR($A16="",'04 Prices'!F16="",'04 Prices'!F17=""),"",LN('04 Prices'!F17/'04 Prices'!F16)) | G16: =IF(OR($A16="",'04 Prices'!G16="",'04 Prices'!G17=""),"",LN('04 Prices'!G17/'04 Prices'!G16)) | H16: =IF(OR($A16="",'04 Prices'!H16="",'04 Prices'!H17=""),"",LN('04 Prices'!H17/'04 Prices'!H16))
... A723: =IF('04 Prices'!A724="","",'04 Prices'!A724) | B723: =IF(OR($A723="",'04 Prices'!B723="",'04 Prices'!B724=""),"",LN('04 Prices'!B724/'04 Prices'!B723)) | C723: =IF(OR($A723="",'04 Prices'!C723="",'04 Prices'!C724=""),"",LN('04 Prices'!C724/'04 Prices'!C723)) | D723: =IF(OR($A723="",'04 Prices'!D723="",'04 Prices'!D724=""),"",LN('04 Prices'!D724/'04 Prices'!D723)) | E723: =IF(OR($A723="",'04 Prices'!E723="",'04 Prices'!E724=""),"",LN('04 Prices'!E724/'04 Prices'!E723)) | F723: =IF(OR($A723="",'04 Prices'!F723="",'04 Prices'!F724=""),"",LN('04 Prices'!F724/'04 Prices'!F723)) | G723: =IF(OR($A723="",'04 Prices'!G723="",'04 Prices'!G724=""),"",LN('04 Prices'!G724/'04 Prices'!G723)) | H723: =IF(OR($A723="",'04 Prices'!H723="",'04 Prices'!H724=""),"",LN('04 Prices'!H724/'04 Prices'!H723))

Sheet 07 Annualised Inputs
A1: Annualised Optimisation Inputs
A2: The two objects Markowitz mean-variance optimisation needs: the vector of annualised expected returns (mu) and the annualised covariance matrix (Sigma). Both are built from LOG returns.
A3: Mirrors: optimization.py -> annualized_inputs(log_return_df)
A5: STEP 1 — ANNUALISED EXPECTED RETURNS mu = mean(daily log return) x 252
A6: Asset | B6: Mean daily log return | C6: Trading days | D6: Annualised expected return (mu)
A7: JPM | B7: =AVERAGE('06 Log Returns'!$B$5:$B$723) | C7: ='02 Config'!$B$12 | D7: =B7*C7
A8: MS | B8: =AVERAGE('06 Log Returns'!$C$5:$C$723) | C8: ='02 Config'!$B$12 | D8: =B8*C8
A9: BAC | B9: =AVERAGE('06 Log Returns'!$D$5:$D$723) | C9: ='02 Config'!$B$12 | D9: =B9*C9
A10: AAPL | B10: =AVERAGE('06 Log Returns'!$E$5:$E$723) | C10: ='02 Config'!$B$12 | D10: =B10*C10
A11: MSFT | B11: =AVERAGE('06 Log Returns'!$F$5:$F$723) | C11: ='02 Config'!$B$12 | D11: =B11*C11
A12: GLD | B12: =AVERAGE('06 Log Returns'!$G$5:$G$723) | C12: ='02 Config'!$B$12 | D12: =B12*C12
A15: STEP 2 — ANNUALISED COVARIANCE MATRIX Sigma = cov(daily log returns) x 252
A16: Asset | B16: JPM | C16: MS | D16: BAC | E16: AAPL | F16: MSFT | G16: GLD
A17: JPM | B17: {=SUMPRODUCT(IF('06 Log Returns'!$B$5:$B$723="",0,'06 Log Returns'!$B$5:$B$723-AVERAGE('06 Log Returns'!$B$5:$B$723)),IF('06 Log Returns'!$B$5:$B$723="",0,'06 Log Returns'!$B$5:$B$723-AVERAGE('06 Log Returns'!$B$5:$B$723)))/(COUNT('06 Log Returns'!$B$5:$B$723)-1)*'02 Config'!$B$12} | C17: {=SUMPRODUCT(IF('06 Log Returns'!$B$5:$B$723="",0,'06 Log Returns'!$B$5:$B$723-AVERAGE('06 Log Returns'!$B$5:$B$723)),IF('06 Log Returns'!$C$5:$C$723="",0,'06 Log Returns'!$C$5:$C$723-AVERAGE('06 Log Returns'!$C$5:$C$723)))/(COUNT('06 Log Returns'!$B$5:$B$723)-1)*'02 Config'!$B$12} | D17: {=SUMPRODUCT(IF('06 Log Returns'!$B$5:$B$723="",0,'06 Log Returns'!$B$5:$B$723-AVERAGE('06 Log Returns'!$B$5:$B$723)),IF('06 Log Returns'!$D$5:$D$723="",0,'06 Log Returns'!$D$5:$D$723-AVERAGE('06 Log Returns'!$D$5:$D$723)))/(COUNT('06 Log Returns'!$B$5:$B$723)-1)*'02 Config'!$B$12} | E17: {=SUMPRODUCT(IF('06 Log Returns'!$B$5:$B$723="",0,'06 Log Returns'!$B$5:$B$723-AVERAGE('06 Log Returns'!$B$5:$B$723)),IF('06 Log Returns'!$E$5:$E$723="",0,'06 Log Returns'!$E$5:$E$723-AVERAGE('06 Log Returns'!$E$5:$E$723)))/(COUNT('06 Log Returns'!$B$5:$B$723)-1)*'02 Config'!$B$12} | F17: {=SUMPRODUCT(IF('06 Log Returns'!$B$5:$B$723="",0,'06 Log Returns'!$B$5:$B$723-AVERAGE('06 Log Returns'!$B$5:$B$723)),IF('06 Log Returns'!$F$5:$F$723="",0,'06 Log Returns'!$F$5:$F$723-AVERAGE('06 Log Returns'!$F$5:$F$723)))/(COUNT('06 Log Returns'!$B$5:$B$723)-1)*'02 Config'!$B$12} | G17: {=SUMPRODUCT(IF('06 Log Returns'!$B$5:$B$723="",0,'06 Log Returns'!$B$5:$B$723-AVERAGE('06 Log Returns'!$B$5:$B$723)),IF('06 Log Returns'!$G$5:$G$723="",0,'06 Log Returns'!$G$5:$G$723-AVERAGE('06 Log Returns'!$G$5:$G$723)))/(COUNT('06 Log Returns'!$B$5:$B$723)-1)*'02 Config'!$B$12}
A18: MS | B18: {=SUMPRODUCT(IF('06 Log Returns'!$C$5:$C$723="",0,'06 Log Returns'!$C$5:$C$723-AVERAGE('06 Log Returns'!$C$5:$C$723)),IF('06 Log Returns'!$B$5:$B$723="",0,'06 Log Returns'!$B$5:$B$723-AVERAGE('06 Log Returns'!$B$5:$B$723)))/(COUNT('06 Log Returns'!$C$5:$C$723)-1)*'02 Config'!$B$12} | C18: {=SUMPRODUCT(IF('06 Log Returns'!$C$5:$C$723="",0,'06 Log Returns'!$C$5:$C$723-AVERAGE('06 Log Returns'!$C$5:$C$723)),IF('06 Log Returns'!$C$5:$C$723="",0,'06 Log Returns'!$C$5:$C$723-AVERAGE('06 Log Returns'!$C$5:$C$723)))/(COUNT('06 Log Returns'!$C$5:$C$723)-1)*'02 Config'!$B$12} | D18: {=SUMPRODUCT(IF('06 Log Returns'!$C$5:$C$723="",0,'06 Log Returns'!$C$5:$C$723-AVERAGE('06 Log Returns'!$C$5:$C$723)),IF('06 Log Returns'!$D$5:$D$723="",0,'06 Log Returns'!$D$5:$D$723-AVERAGE('06 Log Returns'!$D$5:$D$723)))/(COUNT('06 Log Returns'!$C$5:$C$723)-1)*'02 Config'!$B$12} | E18: {=SUMPRODUCT(IF('06 Log Returns'!$C$5:$C$723="",0,'06 Log Returns'!$C$5:$C$723-AVERAGE('06 Log Returns'!$C$5:$C$723)),IF('06 Log Returns'!$E$5:$E$723="",0,'06 Log Returns'!$E$5:$E$723-AVERAGE('06 Log Returns'!$E$5:$E$723)))/(COUNT('06 Log Returns'!$C$5:$C$723)-1)*'02 Config'!$B$12} | F18: {=SUMPRODUCT(IF('06 Log Returns'!$C$5:$C$723="",0,'06 Log Returns'!$C$5:$C$723-AVERAGE('06 Log Returns'!$C$5:$C$723)),IF('06 Log Returns'!$F$5:$F$723="",0,'06 Log Returns'!$F$5:$F$723-AVERAGE('06 Log Returns'!$F$5:$F$723)))/(COUNT('06 Log Returns'!$C$5:$C$723)-1)*'02 Config'!$B$12} | G18: {=SUMPRODUCT(IF('06 Log Returns'!$C$5:$C$723="",0,'06 Log Returns'!$C$5:$C$723-AVERAGE('06 Log Returns'!$C$5:$C$723)),IF('06 Log Returns'!$G$5:$G$723="",0,'06 Log Returns'!$G$5:$G$723-AVERAGE('06 Log Returns'!$G$5:$G$723)))/(COUNT('06 Log Returns'!$C$5:$C$723)-1)*'02 Config'!$B$12}
A19: BAC | B19: {=SUMPRODUCT(IF('06 Log Returns'!$D$5:$D$723="",0,'06 Log Returns'!$D$5:$D$723-AVERAGE('06 Log Returns'!$D$5:$D$723)),IF('06 Log Returns'!$B$5:$B$723="",0,'06 Log Returns'!$B$5:$B$723-AVERAGE('06 Log Returns'!$B$5:$B$723)))/(COUNT('06 Log Returns'!$D$5:$D$723)-1)*'02 Config'!$B$12} | C19: {=SUMPRODUCT(IF('06 Log Returns'!$D$5:$D$723="",0,'06 Log Returns'!$D$5:$D$723-AVERAGE('06 Log Returns'!$D$5:$D$723)),IF('06 Log Returns'!$C$5:$C$723="",0,'06 Log Returns'!$C$5:$C$723-AVERAGE('06 Log Returns'!$C$5:$C$723)))/(COUNT('06 Log Returns'!$D$5:$D$723)-1)*'02 Config'!$B$12} | D19: {=SUMPRODUCT(IF('06 Log Returns'!$D$5:$D$723="",0,'06 Log Returns'!$D$5:$D$723-AVERAGE('06 Log Returns'!$D$5:$D$723)),IF('06 Log Returns'!$D$5:$D$723="",0,'06 Log Returns'!$D$5:$D$723-AVERAGE('06 Log Returns'!$D$5:$D$723)))/(COUNT('06 Log Returns'!$D$5:$D$723)-1)*'02 Config'!$B$12} | E19: {=SUMPRODUCT(IF('06 Log Returns'!$D$5:$D$723="",0,'06 Log Returns'!$D$5:$D$723-AVERAGE('06 Log Returns'!$D$5:$D$723)),IF('06 Log Returns'!$E$5:$E$723="",0,'06 Log Returns'!$E$5:$E$723-AVERAGE('06 Log Returns'!$E$5:$E$723)))/(COUNT('06 Log Returns'!$D$5:$D$723)-1)*'02 Config'!$B$12} | F19: {=SUMPRODUCT(IF('06 Log Returns'!$D$5:$D$723="",0,'06 Log Returns'!$D$5:$D$723-AVERAGE('06 Log Returns'!$D$5:$D$723)),IF('06 Log Returns'!$F$5:$F$723="",0,'06 Log Returns'!$F$5:$F$723-AVERAGE('06 Log Returns'!$F$5:$F$723)))/(COUNT('06 Log Returns'!$D$5:$D$723)-1)*'02 Config'!$B$12} | G19: {=SUMPRODUCT(IF('06 Log Returns'!$D$5:$D$723="",0,'06 Log Returns'!$D$5:$D$723-AVERAGE('06 Log Returns'!$D$5:$D$723)),IF('06 Log Returns'!$G$5:$G$723="",0,'06 Log Returns'!$G$5:$G$723-AVERAGE('06 Log Returns'!$G$5:$G$723)))/(COUNT('06 Log Returns'!$D$5:$D$723)-1)*'02 Config'!$B$12}
A20: AAPL | B20: {=SUMPRODUCT(IF('06 Log Returns'!$E$5:$E$723="",0,'06 Log Returns'!$E$5:$E$723-AVERAGE('06 Log Returns'!$E$5:$E$723)),IF('06 Log Returns'!$B$5:$B$723="",0,'06 Log Returns'!$B$5:$B$723-AVERAGE('06 Log Returns'!$B$5:$B$723)))/(COUNT('06 Log Returns'!$E$5:$E$723)-1)*'02 Config'!$B$12} | C20: {=SUMPRODUCT(IF('06 Log Returns'!$E$5:$E$723="",0,'06 Log Returns'!$E$5:$E$723-AVERAGE('06 Log Returns'!$E$5:$E$723)),IF('06 Log Returns'!$C$5:$C$723="",0,'06 Log Returns'!$C$5:$C$723-AVERAGE('06 Log Returns'!$C$5:$C$723)))/(COUNT('06 Log Returns'!$E$5:$E$723)-1)*'02 Config'!$B$12} | D20: {=SUMPRODUCT(IF('06 Log Returns'!$E$5:$E$723="",0,'06 Log Returns'!$E$5:$E$723-AVERAGE('06 Log Returns'!$E$5:$E$723)),IF('06 Log Returns'!$D$5:$D$723="",0,'06 Log Returns'!$D$5:$D$723-AVERAGE('06 Log Returns'!$D$5:$D$723)))/(COUNT('06 Log Returns'!$E$5:$E$723)-1)*'02 Config'!$B$12} | E20: {=SUMPRODUCT(IF('06 Log Returns'!$E$5:$E$723="",0,'06 Log Returns'!$E$5:$E$723-AVERAGE('06 Log Returns'!$E$5:$E$723)),IF('06 Log Returns'!$E$5:$E$723="",0,'06 Log Returns'!$E$5:$E$723-AVERAGE('06 Log Returns'!$E$5:$E$723)))/(COUNT('06 Log Returns'!$E$5:$E$723)-1)*'02 Config'!$B$12} | F20: {=SUMPRODUCT(IF('06 Log Returns'!$E$5:$E$723="",0,'06 Log Returns'!$E$5:$E$723-AVERAGE('06 Log Returns'!$E$5:$E$723)),IF('06 Log Returns'!$F$5:$F$723="",0,'06 Log Returns'!$F$5:$F$723-AVERAGE('06 Log Returns'!$F$5:$F$723)))/(COUNT('06 Log Returns'!$E$5:$E$723)-1)*'02 Config'!$B$12} | G20: {=SUMPRODUCT(IF('06 Log Returns'!$E$5:$E$723="",0,'06 Log Returns'!$E$5:$E$723-AVERAGE('06 Log Returns'!$E$5:$E$723)),IF('06 Log Returns'!$G$5:$G$723="",0,'06 Log Returns'!$G$5:$G$723-AVERAGE('06 Log Returns'!$G$5:$G$723)))/(COUNT('06 Log Returns'!$E$5:$E$723)-1)*'02 Config'!$B$12}
A21: MSFT | B21: {=SUMPRODUCT(IF('06 Log Returns'!$F$5:$F$723="",0,'06 Log Returns'!$F$5:$F$723-AVERAGE('06 Log Returns'!$F$5:$F$723)),IF('06 Log Returns'!$B$5:$B$723="",0,'06 Log Returns'!$B$5:$B$723-AVERAGE('06 Log Returns'!$B$5:$B$723)))/(COUNT('06 Log Returns'!$F$5:$F$723)-1)*'02 Config'!$B$12} | C21: {=SUMPRODUCT(IF('06 Log Returns'!$F$5:$F$723="",0,'06 Log Returns'!$F$5:$F$723-AVERAGE('06 Log Returns'!$F$5:$F$723)),IF('06 Log Returns'!$C$5:$C$723="",0,'06 Log Returns'!$C$5:$C$723-AVERAGE('06 Log Returns'!$C$5:$C$723)))/(COUNT('06 Log Returns'!$F$5:$F$723)-1)*'02 Config'!$B$12} | D21: {=SUMPRODUCT(IF('06 Log Returns'!$F$5:$F$723="",0,'06 Log Returns'!$F$5:$F$723-AVERAGE('06 Log Returns'!$F$5:$F$723)),IF('06 Log Returns'!$D$5:$D$723="",0,'06 Log Returns'!$D$5:$D$723-AVERAGE('06 Log Returns'!$D$5:$D$723)))/(COUNT('06 Log Returns'!$F$5:$F$723)-1)*'02 Config'!$B$12} | E21: {=SUMPRODUCT(IF('06 Log Returns'!$F$5:$F$723="",0,'06 Log Returns'!$F$5:$F$723-AVERAGE('06 Log Returns'!$F$5:$F$723)),IF('06 Log Returns'!$E$5:$E$723="",0,'06 Log Returns'!$E$5:$E$723-AVERAGE('06 Log Returns'!$E$5:$E$723)))/(COUNT('06 Log Returns'!$F$5:$F$723)-1)*'02 Config'!$B$12} | F21: {=SUMPRODUCT(IF('06 Log Returns'!$F$5:$F$723="",0,'06 Log Returns'!$F$5:$F$723-AVERAGE('06 Log Returns'!$F$5:$F$723)),IF('06 Log Returns'!$F$5:$F$723="",0,'06 Log Returns'!$F$5:$F$723-AVERAGE('06 Log Returns'!$F$5:$F$723)))/(COUNT('06 Log Returns'!$F$5:$F$723)-1)*'02 Config'!$B$12} | G21: {=SUMPRODUCT(IF('06 Log Returns'!$F$5:$F$723="",0,'06 Log Returns'!$F$5:$F$723-AVERAGE('06 Log Returns'!$F$5:$F$723)),IF('06 Log Returns'!$G$5:$G$723="",0,'06 Log Returns'!$G$5:$G$723-AVERAGE('06 Log Returns'!$G$5:$G$723)))/(COUNT('06 Log Returns'!$F$5:$F$723)-1)*'02 Config'!$B$12}
A22: GLD | B22: {=SUMPRODUCT(IF('06 Log Returns'!$G$5:$G$723="",0,'06 Log Returns'!$G$5:$G$723-AVERAGE('06 Log Returns'!$G$5:$G$723)),IF('06 Log Returns'!$B$5:$B$723="",0,'06 Log Returns'!$B$5:$B$723-AVERAGE('06 Log Returns'!$B$5:$B$723)))/(COUNT('06 Log Returns'!$G$5:$G$723)-1)*'02 Config'!$B$12} | C22: {=SUMPRODUCT(IF('06 Log Returns'!$G$5:$G$723="",0,'06 Log Returns'!$G$5:$G$723-AVERAGE('06 Log Returns'!$G$5:$G$723)),IF('06 Log Returns'!$C$5:$C$723="",0,'06 Log Returns'!$C$5:$C$723-AVERAGE('06 Log Returns'!$C$5:$C$723)))/(COUNT('06 Log Returns'!$G$5:$G$723)-1)*'02 Config'!$B$12} | D22: {=SUMPRODUCT(IF('06 Log Returns'!$G$5:$G$723="",0,'06 Log Returns'!$G$5:$G$723-AVERAGE('06 Log Returns'!$G$5:$G$723)),IF('06 Log Returns'!$D$5:$D$723="",0,'06 Log Returns'!$D$5:$D$723-AVERAGE('06 Log Returns'!$D$5:$D$723)))/(COUNT('06 Log Returns'!$G$5:$G$723)-1)*'02 Config'!$B$12} | E22: {=SUMPRODUCT(IF('06 Log Returns'!$G$5:$G$723="",0,'06 Log Returns'!$G$5:$G$723-AVERAGE('06 Log Returns'!$G$5:$G$723)),IF('06 Log Returns'!$E$5:$E$723="",0,'06 Log Returns'!$E$5:$E$723-AVERAGE('06 Log Returns'!$E$5:$E$723)))/(COUNT('06 Log Returns'!$G$5:$G$723)-1)*'02 Config'!$B$12} | F22: {=SUMPRODUCT(IF('06 Log Returns'!$G$5:$G$723="",0,'06 Log Returns'!$G$5:$G$723-AVERAGE('06 Log Returns'!$G$5:$G$723)),IF('06 Log Returns'!$F$5:$F$723="",0,'06 Log Returns'!$F$5:$F$723-AVERAGE('06 Log Returns'!$F$5:$F$723)))/(COUNT('06 Log Returns'!$G$5:$G$723)-1)*'02 Config'!$B$12} | G22: {=SUMPRODUCT(IF('06 Log Returns'!$G$5:$G$723="",0,'06 Log Returns'!$G$5:$G$723-AVERAGE('06 Log Returns'!$G$5:$G$723)),IF('06 Log Returns'!$G$5:$G$723="",0,'06 Log Returns'!$G$5:$G$723-AVERAGE('06 Log Returns'!$G$5:$G$723)))/(COUNT('06 Log Returns'!$G$5:$G$723)-1)*'02 Config'!$B$12}
A25: STEP 3 — CORRELATION MATRIX (diagnostic — not used by the optimiser)
A26: Asset | B26: JPM | C26: MS | D26: BAC | E26: AAPL | F26: MSFT | G26: GLD
A27: JPM | B27: =$B$17/(SQRT($B$17)*SQRT($B$17)) | C27: =$C$17/(SQRT($B$17)*SQRT($C$18)) | D27: =$D$17/(SQRT($B$17)*SQRT($D$19)) | E27: =$E$17/(SQRT($B$17)*SQRT($E$20)) | F27: =$F$17/(SQRT($B$17)*SQRT($F$21)) | G27: =$G$17/(SQRT($B$17)*SQRT($G$22))
A28: MS | B28: =$B$18/(SQRT($C$18)*SQRT($B$17)) | C28: =$C$18/(SQRT($C$18)*SQRT($C$18)) | D28: =$D$18/(SQRT($C$18)*SQRT($D$19)) | E28: =$E$18/(SQRT($C$18)*SQRT($E$20)) | F28: =$F$18/(SQRT($C$18)*SQRT($F$21)) | G28: =$G$18/(SQRT($C$18)*SQRT($G$22))
A29: BAC | B29: =$B$19/(SQRT($D$19)*SQRT($B$17)) | C29: =$C$19/(SQRT($D$19)*SQRT($C$18)) | D29: =$D$19/(SQRT($D$19)*SQRT($D$19)) | E29: =$E$19/(SQRT($D$19)*SQRT($E$20)) | F29: =$F$19/(SQRT($D$19)*SQRT($F$21)) | G29: =$G$19/(SQRT($D$19)*SQRT($G$22))
A30: AAPL | B30: =$B$20/(SQRT($E$20)*SQRT($B$17)) | C30: =$C$20/(SQRT($E$20)*SQRT($C$18)) | D30: =$D$20/(SQRT($E$20)*SQRT($D$19)) | E30: =$E$20/(SQRT($E$20)*SQRT($E$20)) | F30: =$F$20/(SQRT($E$20)*SQRT($F$21)) | G30: =$G$20/(SQRT($E$20)*SQRT($G$22))
A31: MSFT | B31: =$B$21/(SQRT($F$21)*SQRT($B$17)) | C31: =$C$21/(SQRT($F$21)*SQRT($C$18)) | D31: =$D$21/(SQRT($F$21)*SQRT($D$19)) | E31: =$E$21/(SQRT($F$21)*SQRT($E$20)) | F31: =$F$21/(SQRT($F$21)*SQRT($F$21)) | G31: =$G$21/(SQRT($F$21)*SQRT($G$22))
A32: GLD | B32: =$B$22/(SQRT($G$22)*SQRT($B$17)) | C32: =$C$22/(SQRT($G$22)*SQRT($C$18)) | D32: =$D$22/(SQRT($G$22)*SQRT($D$19)) | E32: =$E$22/(SQRT($G$22)*SQRT($E$20)) | F32: =$F$22/(SQRT($G$22)*SQRT($F$21)) | G32: =$G$22/(SQRT($G$22)*SQRT($G$22))

Sheet 08 Optimisation
A1: Markowitz Mean-Variance Optimisation — Closed Form
A2: Solved with matrix algebra (MINVERSE / MMULT) rather than a numerical optimiser, so every weight is a live formula. This is the UNCONSTRAINED solution: weights may go negative (short positions).
A3: Mirrors: optimization.py -> PortfolioMath, minimum_volatility_portfolio(), maximum_sharpe_portfolio(), efficient_frontier()
A4: IMPORTANT — how this differs from the Python project: optimization.py constrains weights to [0, 1] (long-only) and solves numerically with SciPy's SLSQP. A bounded problem like that has no closed form. The matrix solution below is the analytically exact answer to the SAME objective WITHOUT the bounds, so where a short position would improve the portfolio these weights will differ from the Python output.
A6: STEP 1 — INVERT THE COVARIANCE MATRIX (Sigma^-1)
A7: Asset | B7: JPM | C7: MS | D7: BAC | E7: AAPL | F7: MSFT | G7: GLD
A8: JPM | B8: {=MINVERSE('07 Annualised Inputs'!$B$17:$G$22)}
A9: MS
A10: BAC
A11: AAPL
A12: MSFT
A13: GLD
A16: STEP 2 — THE THREE BUILDING-BLOCK VECTORS
A17: Asset | B17: Sigma^-1 . 1 | C17: Sigma^-1 . mu | D17: Sigma^-1 . (mu - rf.1)
A18: JPM | B18: =SUM(B8:G8) | C18: =SUM(MMULT(B8:G8,'07 Annualised Inputs'!$D$7:$D$12)) | D18: =C18-'02 Config'!$B$10*B18
A19: MS | B19: =SUM(B9:G9) | C19: =SUM(MMULT(B9:G9,'07 Annualised Inputs'!$D$7:$D$12)) | D19: =C19-'02 Config'!$B$10*B19
A20: BAC | B20: =SUM(B10:G10) | C20: =SUM(MMULT(B10:G10,'07 Annualised Inputs'!$D$7:$D$12)) | D20: =C20-'02 Config'!$B$10*B20
A21: AAPL | B21: =SUM(B11:G11) | C21: =SUM(MMULT(B11:G11,'07 Annualised Inputs'!$D$7:$D$12)) | D21: =C21-'02 Config'!$B$10*B21
A22: MSFT | B22: =SUM(B12:G12) | C22: =SUM(MMULT(B12:G12,'07 Annualised Inputs'!$D$7:$D$12)) | D22: =C22-'02 Config'!$B$10*B22
A23: GLD | B23: =SUM(B13:G13) | C23: =SUM(MMULT(B13:G13,'07 Annualised Inputs'!$D$7:$D$12)) | D23: =C23-'02 Config'!$B$10*B23
A26: STEP 3 — THE FOUR SCALAR CONSTANTS OF THE FRONTIER
A27: Constant | B27: Value | C27: Definition | D27: Meaning
A28: A | B28: =SUM(B18:B23) | C28: 1' Sigma^-1 1 | D28: Total 'precision' available. 1/A is the variance of the global minimum-variance portfolio.
A29: B | B29: =SUM(C18:C23) | C29: 1' Sigma^-1 mu | D29: Links the return vector to the weighting scheme. B/A is the min-variance portfolio's expected return.
A30: C | B30: =SUMPRODUCT('07 Annualised Inputs'!$D$7:$D$12,C18:C23) | C30: mu' Sigma^-1 mu | D30: Risk-adjusted magnitude of the expected-return vector.
A31: D | B31: =B28*B30-B29^2 | C31: A.C - B^2 | D31: The frontier's curvature. Positive whenever Sigma is well behaved; it is the denominator of the frontier equation.
A33: STEP 4 — MINIMUM VARIANCE PORTFOLIO w = (Sigma^-1 . 1) / A
A34: These are the weights the rest of the workbook uses as THE portfolio, exactly as main.py does.
A35: Asset | B35: Weight
A36: JPM | B36: =B18/$B$28
A37: MS | B37: =B19/$B$28
A38: BAC | B38: =B20/$B$28
A39: AAPL | B39: =B21/$B$28
A40: MSFT | B40: =B22/$B$28
A41: GLD | B41: =B23/$B$28
A42: Sum of weights (must equal 100%) | B42: =SUM(B36:B41)
A43: Expected annual return | B43: =SUMPRODUCT('07 Annualised Inputs'!$D$7:$D$12,'08 Optimisation'!$B$36:$B$41)
A44: Annual volatility (risk) | B44: =SQRT(SUMPRODUCT(MMULT(TRANSPOSE('08 Optimisation'!$B$36:$B$41),'07 Annualised Inputs'!$B$17:$G$22),TRANSPOSE('08 Optimisation'!$B$36:$B$41)))
A45: Sharpe ratio | B45: =(B43-'02 Config'!$B$10)/B44
A48: STEP 5 — MAXIMUM SHARPE (TANGENCY) PORTFOLIO w = Sigma^-1 (mu - rf.1) / 1'Sigma^-1 (mu - rf.1)
A49: Asset | B49: Weight
A50: JPM | B50: =D18/SUM($D$18:$D$23)
A51: MS | B51: =D19/SUM($D$18:$D$23)
A52: BAC | B52: =D20/SUM($D$18:$D$23)
A53: AAPL | B53: =D21/SUM($D$18:$D$23)
A54: MSFT | B54: =D22/SUM($D$18:$D$23)
A55: GLD | B55: =D23/SUM($D$18:$D$23)
A56: Sum of weights (must equal 100%) | B56: =SUM(B50:B55)
A57: Expected annual return | B57: =SUMPRODUCT('07 Annualised Inputs'!$D$7:$D$12,'08 Optimisation'!$B$50:$B$55)
A58: Annual volatility (risk) | B58: =SQRT(SUMPRODUCT(MMULT(TRANSPOSE('08 Optimisation'!$B$50:$B$55),'07 Annualised Inputs'!$B$17:$G$22),TRANSPOSE('08 Optimisation'!$B$50:$B$55)))
A59: Sharpe ratio | B59: =(B57-'02 Config'!$B$10)/B58
A62: STEP 6 — THE EFFICIENT FRONTIER sigma(r)^2 = (A r^2 - 2 B r + C) / D
A63: 100 target returns spread evenly between the lowest and highest return found by the Monte Carlo simulation on sheet '09 Monte Carlo', matching how main.py builds its target range.
A64: # | B64: Target annual return | C64: Minimum volatility | D64: Sharpe at this point
A65: 1 | B65: =MIN('09 Monte Carlo'!$O$6:$O$1005)+(MAX('09 Monte Carlo'!$O$6:$O$1005)-MIN('09 Monte Carlo'!$O$6:$O$1005))*(A65-1)/('02 Config'!$B$17-1) | C65: =SQRT(($B$28*B65^2-2*$B$29*B65+$B$30)/$B$31) | D65: =(B65-'02 Config'!$B$10)/C65
A66: 2 | B66: =MIN('09 Monte Carlo'!$O$6:$O$1005)+(MAX('09 Monte Carlo'!$O$6:$O$1005)-MIN('09 Monte Carlo'!$O$6:$O$1005))*(A66-1)/('02 Config'!$B$17-1) | C66: =SQRT(($B$28*B66^2-2*$B$29*B66+$B$30)/$B$31) | D66: =(B66-'02 Config'!$B$10)/C66
A67: 3 | B67: =MIN('09 Monte Carlo'!$O$6:$O$1005)+(MAX('09 Monte Carlo'!$O$6:$O$1005)-MIN('09 Monte Carlo'!$O$6:$O$1005))*(A67-1)/('02 Config'!$B$17-1) | C67: =SQRT(($B$28*B67^2-2*$B$29*B67+$B$30)/$B$31) | D67: =(B67-'02 Config'!$B$10)/C67
A68: 4 | B68: =MIN('09 Monte Carlo'!$O$6:$O$1005)+(MAX('09 Monte Carlo'!$O$6:$O$1005)-MIN('09 Monte Carlo'!$O$6:$O$1005))*(A68-1)/('02 Config'!$B$17-1) | C68: =SQRT(($B$28*B68^2-2*$B$29*B68+$B$30)/$B$31) | D68: =(B68-'02 Config'!$B$10)/C68
A69: 5 | B69: =MIN('09 Monte Carlo'!$O$6:$O$1005)+(MAX('09 Monte Carlo'!$O$6:$O$1005)-MIN('09 Monte Carlo'!$O$6:$O$1005))*(A69-1)/('02 Config'!$B$17-1) | C69: =SQRT(($B$28*B69^2-2*$B$29*B69+$B$30)/$B$31) | D69: =(B69-'02 Config'!$B$10)/C69
A70: 6 | B70: =MIN('09 Monte Carlo'!$O$6:$O$1005)+(MAX('09 Monte Carlo'!$O$6:$O$1005)-MIN('09 Monte Carlo'!$O$6:$O$1005))*(A70-1)/('02 Config'!$B$17-1) | C70: =SQRT(($B$28*B70^2-2*$B$29*B70+$B$30)/$B$31) | D70: =(B70-'02 Config'!$B$10)/C70
A71: 7 | B71: =MIN('09 Monte Carlo'!$O$6:$O$1005)+(MAX('09 Monte Carlo'!$O$6:$O$1005)-MIN('09 Monte Carlo'!$O$6:$O$1005))*(A71-1)/('02 Config'!$B$17-1) | C71: =SQRT(($B$28*B71^2-2*$B$29*B71+$B$30)/$B$31) | D71: =(B71-'02 Config'!$B$10)/C71
A72: 8 | B72: =MIN('09 Monte Carlo'!$O$6:$O$1005)+(MAX('09 Monte Carlo'!$O$6:$O$1005)-MIN('09 Monte Carlo'!$O$6:$O$1005))*(A72-1)/('02 Config'!$B$17-1) | C72: =SQRT(($B$28*B72^2-2*$B$29*B72+$B$30)/$B$31) | D72: =(B72-'02 Config'!$B$10)/C72
A73: 9 | B73: =MIN('09 Monte Carlo'!$O$6:$O$1005)+(MAX('09 Monte Carlo'!$O$6:$O$1005)-MIN('09 Monte Carlo'!$O$6:$O$1005))*(A73-1)/('02 Config'!$B$17-1) | C73: =SQRT(($B$28*B73^2-2*$B$29*B73+$B$30)/$B$31) | D73: =(B73-'02 Config'!$B$10)/C73
A74: 10 | B74: =MIN('09 Monte Carlo'!$O$6:$O$1005)+(MAX('09 Monte Carlo'!$O$6:$O$1005)-MIN('09 Monte Carlo'!$O$6:$O$1005))*(A74-1)/('02 Config'!$B$17-1) | C74: =SQRT(($B$28*B74^2-2*$B$29*B74+$B$30)/$B$31) | D74: =(B74-'02 Config'!$B$10)/C74
A75: 11 | B75: =MIN('09 Monte Carlo'!$O$6:$O$1005)+(MAX('09 Monte Carlo'!$O$6:$O$1005)-MIN('09 Monte Carlo'!$O$6:$O$1005))*(A75-1)/('02 Config'!$B$17-1) | C75: =SQRT(($B$28*B75^2-2*$B$29*B75+$B$30)/$B$31) | D75: =(B75-'02 Config'!$B$10)/C75
A76: 12 | B76: =MIN('09 Monte Carlo'!$O$6:$O$1005)+(MAX('09 Monte Carlo'!$O$6:$O$1005)-MIN('09 Monte Carlo'!$O$6:$O$1005))*(A76-1)/('02 Config'!$B$17-1) | C76: =SQRT(($B$28*B76^2-2*$B$29*B76+$B$30)/$B$31) | D76: =(B76-'02 Config'!$B$10)/C76
... A164: 100 | B164: =MIN('09 Monte Carlo'!$O$6:$O$1005)+(MAX('09 Monte Carlo'!$O$6:$O$1005)-MIN('09 Monte Carlo'!$O$6:$O$1005))*(A164-1)/('02 Config'!$B$17-1) | C164: =SQRT(($B$28*B164^2-2*$B$29*B164+$B$30)/$B$31) | D164: =(B164-'02 Config'!$B$10)/C164

Sheet 09 Monte Carlo
A1: Monte Carlo Simulation of the Feasible Set
A2: 1,000 randomly weighted long-only portfolios. Plotted as a cloud, they fill in the region of risk/return space a portfolio can actually reach — the efficient frontier is its upper-left edge.
A3: Mirrors: optimization.py -> monte_carlo_portfolios(pm, n_portfolios, seed)
A4: The six blue columns are the raw uniform random draws produced by numpy's default_rng(seed=42) — the same generator and seed as config.py — so these rows reproduce the first rows of the Python simulation exactly. They are pasted as fixed values rather than RAND(), which would reshuffle the cloud on every keystroke and make the charts flicker. Everything to the right of them is live formula.
A5: # | B5: draw JPM | C5: draw MS | D5: draw BAC | E5: draw AAPL | F5: draw MSFT | G5: draw GLD | H5: Sum of draws | I5: w JPM | J5: w MS | K5: w BAC | L5: w AAPL | M5: w MSFT | N5: w GLD | O5: Return | P5: Volatility | Q5: Sharpe | S5: SIMULATION SUMMARY
A6: 1 | B6: 0.77395605 | C6: 0.43887844 | D6: 0.85859792 | E6: 0.69736803 | F6: 0.094177348 | G6: 0.97562235 | H6: =SUM(B6:G6) | I6: =B6/$H6 | J6: =C6/$H6 | K6: =D6/$H6 | L6: =E6/$H6 | M6: =F6/$H6 | N6: =G6/$H6 | O6: =SUM(MMULT(I6:N6,'07 Annualised Inputs'!$D$7:$D$12)) | P6: =SQRT(SUMPRODUCT(MMULT(I6:N6,'07 Annualised Inputs'!$B$17:$G$22),I6:N6)) | Q6: =(O6-'02 Config'!$B$10)/P6 | S6: Lowest simulated return | V6: =MIN($O$6:$O$1005)
A7: 2 | B7: 0.7611397 | C7: 0.78606431 | D7: 0.12811363 | E7: 0.45038594 | F7: 0.37079802 | G7: 0.92676499 | H7: =SUM(B7:G7) | I7: =B7/$H7 | J7: =C7/$H7 | K7: =D7/$H7 | L7: =E7/$H7 | M7: =F7/$H7 | N7: =G7/$H7 | O7: =SUM(MMULT(I7:N7,'07 Annualised Inputs'!$D$7:$D$12)) | P7: =SQRT(SUMPRODUCT(MMULT(I7:N7,'07 Annualised Inputs'!$B$17:$G$22),I7:N7)) | Q7: =(O7-'02 Config'!$B$10)/P7 | S7: Highest simulated return | V7: =MAX($O$6:$O$1005)
A8: 3 | B8: 0.64386512 | C8: 0.82276161 | D8: 0.4434142 | E8: 0.22723872 | F8: 0.55458479 | G8: 0.063817256 | H8: =SUM(B8:G8) | I8: =B8/$H8 | J8: =C8/$H8 | K8: =D8/$H8 | L8: =E8/$H8 | M8: =F8/$H8 | N8: =G8/$H8 | O8: =SUM(MMULT(I8:N8,'07 Annualised Inputs'!$D$7:$D$12)) | P8: =SQRT(SUMPRODUCT(MMULT(I8:N8,'07 Annualised Inputs'!$B$17:$G$22),I8:N8)) | Q8: =(O8-'02 Config'!$B$10)/P8 | S8: Lowest simulated volatility | V8: =MIN($P$6:$P$1005)
A9: 4 | B9: 0.82763117 | C9: 0.6316644 | D9: 0.75808774 | E9: 0.35452597 | F9: 0.97069802 | G9: 0.89312112 | H9: =SUM(B9:G9) | I9: =B9/$H9 | J9: =C9/$H9 | K9: =D9/$H9 | L9: =E9/$H9 | M9: =F9/$H9 | N9: =G9/$H9 | O9: =SUM(MMULT(I9:N9,'07 Annualised Inputs'!$D$7:$D$12)) | P9: =SQRT(SUMPRODUCT(MMULT(I9:N9,'07 Annualised Inputs'!$B$17:$G$22),I9:N9)) | Q9: =(O9-'02 Config'!$B$10)/P9 | S9: Best simulated Sharpe ratio | V9: =MAX($Q$6:$Q$1005)
A10: 5 | B10: 0.7783835 | C10: 0.19463871 | D10: 0.466721 | E10: 0.043803766 | F10: 0.15428949 | G10: 0.68304895 | H10: =SUM(B10:G10) | I10: =B10/$H10 | J10: =C10/$H10 | K10: =D10/$H10 | L10: =E10/$H10 | M10: =F10/$H10 | N10: =G10/$H10 | O10: =SUM(MMULT(I10:N10,'07 Annualised Inputs'!$D$7:$D$12)) | P10: =SQRT(SUMPRODUCT(MMULT(I10:N10,'07 Annualised Inputs'!$B$17:$G$22),I10:N10)) | Q10: =(O10-'02 Config'!$B$10)/P10 | S10: Best Sharpe from the closed-form tangency portfolio | V10: ='08 Optimisation'!$B$59
A11: 6 | B11: 0.74476216 | C11: 0.96750973 | D11: 0.32582536 | E11: 0.37045971 | F11: 0.46955581 | G11: 0.18947136 | H11: =SUM(B11:G11) | I11: =B11/$H11 | J11: =C11/$H11 | K11: =D11/$H11 | L11: =E11/$H11 | M11: =F11/$H11 | N11: =G11/$H11 | O11: =SUM(MMULT(I11:N11,'07 Annualised Inputs'!$D$7:$D$12)) | P11: =SQRT(SUMPRODUCT(MMULT(I11:N11,'07 Annualised Inputs'!$B$17:$G$22),I11:N11)) | Q11: =(O11-'02 Config'!$B$10)/P11
A12: 7 | B12: 0.12992151 | C12: 0.47570493 | D12: 0.22690935 | E12: 0.66981399 | F12: 0.43715192 | G12: 0.8326782 | H12: =SUM(B12:G12) | I12: =B12/$H12 | J12: =C12/$H12 | K12: =D12/$H12 | L12: =E12/$H12 | M12: =F12/$H12 | N12: =G12/$H12 | O12: =SUM(MMULT(I12:N12,'07 Annualised Inputs'!$D$7:$D$12)) | P12: =SQRT(SUMPRODUCT(MMULT(I12:N12,'07 Annualised Inputs'!$B$17:$G$22),I12:N12)) | Q12: =(O12-'02 Config'!$B$10)/P12
A13: 8 | B13: 0.7002651 | C13: 0.31236664 | D13: 0.8322598 | E13: 0.80476436 | F13: 0.38747838 | G13: 0.2883281 | H13: =SUM(B13:G13) | I13: =B13/$H13 | J13: =C13/$H13 | K13: =D13/$H13 | L13: =E13/$H13 | M13: =F13/$H13 | N13: =G13/$H13 | O13: =SUM(MMULT(I13:N13,'07 Annualised Inputs'!$D$7:$D$12)) | P13: =SQRT(SUMPRODUCT(MMULT(I13:N13,'07 Annualised Inputs'!$B$17:$G$22),I13:N13)) | Q13: =(O13-'02 Config'!$B$10)/P13
A14: 9 | B14: 0.6824955 | C14: 0.13975248 | D14: 0.1999082 | E14: 0.0073622698 | F14: 0.78692438 | G14: 0.66485086 | H14: =SUM(B14:G14) | I14: =B14/$H14 | J14: =C14/$H14 | K14: =D14/$H14 | L14: =E14/$H14 | M14: =F14/$H14 | N14: =G14/$H14 | O14: =SUM(MMULT(I14:N14,'07 Annualised Inputs'!$D$7:$D$12)) | P14: =SQRT(SUMPRODUCT(MMULT(I14:N14,'07 Annualised Inputs'!$B$17:$G$22),I14:N14)) | Q14: =(O14-'02 Config'!$B$10)/P14
A15: 10 | B15: 0.70516538 | C15: 0.78072903 | D15: 0.45891578 | E15: 0.5687412 | F15: 0.139797 | G15: 0.11453007 | H15: =SUM(B15:G15) | I15: =B15/$H15 | J15: =C15/$H15 | K15: =D15/$H15 | L15: =E15/$H15 | M15: =F15/$H15 | N15: =G15/$H15 | O15: =SUM(MMULT(I15:N15,'07 Annualised Inputs'!$D$7:$D$12)) | P15: =SQRT(SUMPRODUCT(MMULT(I15:N15,'07 Annualised Inputs'!$B$17:$G$22),I15:N15)) | Q15: =(O15-'02 Config'!$B$10)/P15
A16: 11 | B16: 0.66840296 | C16: 0.47109621 | D16: 0.56523611 | E16: 0.76499886 | F16: 0.63471832 | G16: 0.5535794 | H16: =SUM(B16:G16) | I16: =B16/$H16 | J16: =C16/$H16 | K16: =D16/$H16 | L16: =E16/$H16 | M16: =F16/$H16 | N16: =G16/$H16 | O16: =SUM(MMULT(I16:N16,'07 Annualised Inputs'!$D$7:$D$12)) | P16: =SQRT(SUMPRODUCT(MMULT(I16:N16,'07 Annualised Inputs'!$B$17:$G$22),I16:N16)) | Q16: =(O16-'02 Config'!$B$10)/P16
A17: 12 | B17: 0.55920716 | C17: 0.3039501 | D17: 0.030817835 | E17: 0.43671739 | F17: 0.21458467 | G17: 0.40852864 | H17: =SUM(B17:G17) | I17: =B17/$H17 | J17: =C17/$H17 | K17: =D17/$H17 | L17: =E17/$H17 | M17: =F17/$H17 | N17: =G17/$H17 | O17: =SUM(MMULT(I17:N17,'07 Annualised Inputs'!$D$7:$D$12)) | P17: =SQRT(SUMPRODUCT(MMULT(I17:N17,'07 Annualised Inputs'!$B$17:$G$22),I17:N17)) | Q17: =(O17-'02 Config'!$B$10)/P17
A18: 13 | B18: 0.85340307 | C18: 0.23393949 | D18: 0.058302742 | E18: 0.28138389 | F18: 0.29359376 | G18: 0.66191651 | H18: =SUM(B18:G18) | I18: =B18/$H18 | J18: =C18/$H18 | K18: =D18/$H18 | L18: =E18/$H18 | M18: =F18/$H18 | N18: =G18/$H18 | O18: =SUM(MMULT(I18:N18,'07 Annualised Inputs'!$D$7:$D$12)) | P18: =SQRT(SUMPRODUCT(MMULT(I18:N18,'07 Annualised Inputs'!$B$17:$G$22),I18:N18)) | Q18: =(O18-'02 Config'!$B$10)/P18
A19: 14 | B19: 0.55703215 | C19: 0.78389821 | D19: 0.66431354 | E19: 0.40638686 | F19: 0.81402038 | G19: 0.16697292 | H19: =SUM(B19:G19) | I19: =B19/$H19 | J19: =C19/$H19 | K19: =D19/$H19 | L19: =E19/$H19 | M19: =F19/$H19 | N19: =G19/$H19 | O19: =SUM(MMULT(I19:N19,'07 Annualised Inputs'!$D$7:$D$12)) | P19: =SQRT(SUMPRODUCT(MMULT(I19:N19,'07 Annualised Inputs'!$B$17:$G$22),I19:N19)) | Q19: =(O19-'02 Config'!$B$10)/P19
A20: 15 | B20: 0.022712073 | C20: 0.090047861 | D20: 0.72235935 | E20: 0.46187723 | F20: 0.16127178 | G20: 0.50104478 | H20: =SUM(B20:G20) | I20: =B20/$H20 | J20: =C20/$H20 | K20: =D20/$H20 | L20: =E20/$H20 | M20: =F20/$H20 | N20: =G20/$H20 | O20: =SUM(MMULT(I20:N20,'07 Annualised Inputs'!$D$7:$D$12)) | P20: =SQRT(SUMPRODUCT(MMULT(I20:N20,'07 Annualised Inputs'!$B$17:$G$22),I20:N20)) | Q20: =(O20-'02 Config'!$B$10)/P20
A21: 16 | B21: 0.1523121 | C21: 0.69632038 | D21: 0.44615628 | E21: 0.38102123 | F21: 0.30151209 | G21: 0.63028259 | H21: =SUM(B21:G21) | I21: =B21/$H21 | J21: =C21/$H21 | K21: =D21/$H21 | L21: =E21/$H21 | M21: =F21/$H21 | N21: =G21/$H21 | O21: =SUM(MMULT(I21:N21,'07 Annualised Inputs'!$D$7:$D$12)) | P21: =SQRT(SUMPRODUCT(MMULT(I21:N21,'07 Annualised Inputs'!$B$17:$G$22),I21:N21)) | Q21: =(O21-'02 Config'!$B$10)/P21
A22: 17 | B22: 0.36181261 | C22: 0.087649919 | D22: 0.1180059 | E22: 0.96189766 | F22: 0.90858069 | G22: 0.69970713 | H22: =SUM(B22:G22) | I22: =B22/$H22 | J22: =C22/$H22 | K22: =D22/$H22 | L22: =E22/$H22 | M22: =F22/$H22 | N22: =G22/$H22 | O22: =SUM(MMULT(I22:N22,'07 Annualised Inputs'!$D$7:$D$12)) | P22: =SQRT(SUMPRODUCT(MMULT(I22:N22,'07 Annualised Inputs'!$B$17:$G$22),I22:N22)) | Q22: =(O22-'02 Config'!$B$10)/P22
... A1005: 1000 | B1005: 0.57196084 | C1005: 0.37628074 | D1005: 0.58067767 | E1005: 0.81593106 | F1005: 0.86123734 | G1005: 0.81884388 | H1005: =SUM(B1005:G1005) | I1005: =B1005/$H1005 | J1005: =C1005/$H1005 | K1005: =D1005/$H1005 | L1005: =E1005/$H1005 | M1005: =F1005/$H1005 | N1005: =G1005/$H1005 | O1005: =SUM(MMULT(I1005:N1005,'07 Annualised Inputs'!$D$7:$D$12)) | P1005: =SQRT(SUMPRODUCT(MMULT(I1005:N1005,'07 Annualised Inputs'!$B$17:$G$22),I1005:N1005)) | Q1005: =(O1005-'02 Config'!$B$10)/P1005

Sheet 10 Portfolio Returns
A1: Portfolio Return Series
A2: The six asset return series collapsed into one portfolio series using the minimum-variance weights, then the cumulative growth path and the drawdown series built from it.
A3: Mirrors: returns.py -> portfolio_returns(asset_returns, weights); risk_metrics.py -> max_drawdown()
A4: Date | B4: Portfolio simple return | C4: Portfolio log return | D4: Cumulative growth of $1 | E4: Running peak | F4: Drawdown
A5: =IF('05 Simple Returns'!A5="","",'05 Simple Returns'!A5) | B5: =IF($A5="","",SUM(MMULT('05 Simple Returns'!B5:G5,'08 Optimisation'!$B$36:$B$41))) | C5: =IF($A5="","",SUM(MMULT('06 Log Returns'!B5:G5,'08 Optimisation'!$B$36:$B$41))) | D5: =IF($A5="","",1+B5) | E5: =IF($A5="","",MAX($D$5:D5)) | F5: =IF($A5="","",(E5-D5)/E5)
A6: =IF('05 Simple Returns'!A6="","",'05 Simple Returns'!A6) | B6: =IF($A6="","",SUM(MMULT('05 Simple Returns'!B6:G6,'08 Optimisation'!$B$36:$B$41))) | C6: =IF($A6="","",SUM(MMULT('06 Log Returns'!B6:G6,'08 Optimisation'!$B$36:$B$41))) | D6: =IF($A6="","",IF(D5="","",D5*(1+B6))) | E6: =IF($A6="","",MAX($D$5:D6)) | F6: =IF($A6="","",(E6-D6)/E6)
A7: =IF('05 Simple Returns'!A7="","",'05 Simple Returns'!A7) | B7: =IF($A7="","",SUM(MMULT('05 Simple Returns'!B7:G7,'08 Optimisation'!$B$36:$B$41))) | C7: =IF($A7="","",SUM(MMULT('06 Log Returns'!B7:G7,'08 Optimisation'!$B$36:$B$41))) | D7: =IF($A7="","",IF(D6="","",D6*(1+B7))) | E7: =IF($A7="","",MAX($D$5:D7)) | F7: =IF($A7="","",(E7-D7)/E7)
A8: =IF('05 Simple Returns'!A8="","",'05 Simple Returns'!A8) | B8: =IF($A8="","",SUM(MMULT('05 Simple Returns'!B8:G8,'08 Optimisation'!$B$36:$B$41))) | C8: =IF($A8="","",SUM(MMULT('06 Log Returns'!B8:G8,'08 Optimisation'!$B$36:$B$41))) | D8: =IF($A8="","",IF(D7="","",D7*(1+B8))) | E8: =IF($A8="","",MAX($D$5:D8)) | F8: =IF($A8="","",(E8-D8)/E8)
A9: =IF('05 Simple Returns'!A9="","",'05 Simple Returns'!A9) | B9: =IF($A9="","",SUM(MMULT('05 Simple Returns'!B9:G9,'08 Optimisation'!$B$36:$B$41))) | C9: =IF($A9="","",SUM(MMULT('06 Log Returns'!B9:G9,'08 Optimisation'!$B$36:$B$41))) | D9: =IF($A9="","",IF(D8="","",D8*(1+B9))) | E9: =IF($A9="","",MAX($D$5:D9)) | F9: =IF($A9="","",(E9-D9)/E9)
A10: =IF('05 Simple Returns'!A10="","",'05 Simple Returns'!A10) | B10: =IF($A10="","",SUM(MMULT('05 Simple Returns'!B10:G10,'08 Optimisation'!$B$36:$B$41))) | C10: =IF($A10="","",SUM(MMULT('06 Log Returns'!B10:G10,'08 Optimisation'!$B$36:$B$41))) | D10: =IF($A10="","",IF(D9="","",D9*(1+B10))) | E10: =IF($A10="","",MAX($D$5:D10)) | F10: =IF($A10="","",(E10-D10)/E10)
A11: =IF('05 Simple Returns'!A11="","",'05 Simple Returns'!A11) | B11: =IF($A11="","",SUM(MMULT('05 Simple Returns'!B11:G11,'08 Optimisation'!$B$36:$B$41))) | C11: =IF($A11="","",SUM(MMULT('06 Log Returns'!B11:G11,'08 Optimisation'!$B$36:$B$41))) | D11: =IF($A11="","",IF(D10="","",D10*(1+B11))) | E11: =IF($A11="","",MAX($D$5:D11)) | F11: =IF($A11="","",(E11-D11)/E11)
A12: =IF('05 Simple Returns'!A12="","",'05 Simple Returns'!A12) | B12: =IF($A12="","",SUM(MMULT('05 Simple Returns'!B12:G12,'08 Optimisation'!$B$36:$B$41))) | C12: =IF($A12="","",SUM(MMULT('06 Log Returns'!B12:G12,'08 Optimisation'!$B$36:$B$41))) | D12: =IF($A12="","",IF(D11="","",D11*(1+B12))) | E12: =IF($A12="","",MAX($D$5:D12)) | F12: =IF($A12="","",(E12-D12)/E12)
A13: =IF('05 Simple Returns'!A13="","",'05 Simple Returns'!A13) | B13: =IF($A13="","",SUM(MMULT('05 Simple Returns'!B13:G13,'08 Optimisation'!$B$36:$B$41))) | C13: =IF($A13="","",SUM(MMULT('06 Log Returns'!B13:G13,'08 Optimisation'!$B$36:$B$41))) | D13: =IF($A13="","",IF(D12="","",D12*(1+B13))) | E13: =IF($A13="","",MAX($D$5:D13)) | F13: =IF($A13="","",(E13-D13)/E13)
A14: =IF('05 Simple Returns'!A14="","",'05 Simple Returns'!A14) | B14: =IF($A14="","",SUM(MMULT('05 Simple Returns'!B14:G14,'08 Optimisation'!$B$36:$B$41))) | C14: =IF($A14="","",SUM(MMULT('06 Log Returns'!B14:G14,'08 Optimisation'!$B$36:$B$41))) | D14: =IF($A14="","",IF(D13="","",D13*(1+B14))) | E14: =IF($A14="","",MAX($D$5:D14)) | F14: =IF($A14="","",(E14-D14)/E14)
A15: =IF('05 Simple Returns'!A15="","",'05 Simple Returns'!A15) | B15: =IF($A15="","",SUM(MMULT('05 Simple Returns'!B15:G15,'08 Optimisation'!$B$36:$B$41))) | C15: =IF($A15="","",SUM(MMULT('06 Log Returns'!B15:G15,'08 Optimisation'!$B$36:$B$41))) | D15: =IF($A15="","",IF(D14="","",D14*(1+B15))) | E15: =IF($A15="","",MAX($D$5:D15)) | F15: =IF($A15="","",(E15-D15)/E15)
A16: =IF('05 Simple Returns'!A16="","",'05 Simple Returns'!A16) | B16: =IF($A16="","",SUM(MMULT('05 Simple Returns'!B16:G16,'08 Optimisation'!$B$36:$B$41))) | C16: =IF($A16="","",SUM(MMULT('06 Log Returns'!B16:G16,'08 Optimisation'!$B$36:$B$41))) | D16: =IF($A16="","",IF(D15="","",D15*(1+B16))) | E16: =IF($A16="","",MAX($D$5:D16)) | F16: =IF($A16="","",(E16-D16)/E16)
A17: =IF('05 Simple Returns'!A17="","",'05 Simple Returns'!A17) | B17: =IF($A17="","",SUM(MMULT('05 Simple Returns'!B17:G17,'08 Optimisation'!$B$36:$B$41))) | C17: =IF($A17="","",SUM(MMULT('06 Log Returns'!B17:G17,'08 Optimisation'!$B$36:$B$41))) | D17: =IF($A17="","",IF(D16="","",D16*(1+B17))) | E17: =IF($A17="","",MAX($D$5:D17)) | F17: =IF($A17="","",(E17-D17)/E17)
... A723: =IF('05 Simple Returns'!A723="","",'05 Simple Returns'!A723) | B723: =IF($A723="","",SUM(MMULT('05 Simple Returns'!B723:G723,'08 Optimisation'!$B$36:$B$41))) | C723: =IF($A723="","",SUM(MMULT('06 Log Returns'!B723:G723,'08 Optimisation'!$B$36:$B$41))) | D723: =IF($A723="","",IF(D722="","",D722*(1+B723))) | E723: =IF($A723="","",MAX($D$5:D723)) | F723: =IF($A723="","",(E723-D723)/E723)

Sheet 11 Risk Metrics
A1: Performance & Risk Metrics
A2: Every headline number main.py prints to the console, as a live formula. All of them read the portfolio return series on sheet '10 Portfolio Returns' and the risk-free rate on '02 Config'.
A3: Mirrors: risk_metrics.py + the annualisation helpers in returns.py
A5: RETURN & VOLATILITY
A6: Metric | B6: Value | C6: Formula | D6: What it is / Python source
A7: Mean daily return (simple) | B7: =AVERAGE('10 Portfolio Returns'!$B$5:$B$723) | C7: AVERAGE(daily simple returns) | D7: The arithmetic average day. Blank guard rows are text and are ignored by AVERAGE.
A8: Annualised return (simple) | B8: =(1+B7)^'02 Config'!$B$12-1 | C8: (1 + mean daily)^252 - 1 | D8: Simple returns compound, so annualising raises to the power of 252 rather than multiplying. Python: returns.annualize_simple_return(). This is the return figure every ratio below uses.
A9: Mean daily return (log) | B9: =AVERAGE('10 Portfolio Returns'!$C$5:$C$723) | C9: AVERAGE(daily log returns) | D9: Average continuously compounded day.
A10: Annualised return (log) | B10: =B9*'02 Config'!$B$12 | C10: mean daily log x 252 | D10: Log returns are additive through time, so annualising is a plain multiplication. Python: returns.annualize_log_return(). Always slightly below the simple figure — that gap is the volatility drag.
A11: Daily volatility | B11: =STDEVP('10 Portfolio Returns'!$B$5:$B$723) | C11: STDEVP(daily simple returns) | D11: POPULATION standard deviation (divide by n), because main.py uses np.std() with its default ddof=0. STDEV (sample, n-1) would differ in the fourth decimal — matched deliberately.
A12: Annualised volatility | B12: =B11*SQRT('02 Config'!$B$12) | C12: daily volatility x SQRT(252) | D12: The square-root-of-time rule: variance scales with time, so standard deviation scales with its square root. Python: returns.annualize_volatility().
A15: MARKET-RELATIVE METRICS (vs the benchmark)
A16: Metric | B16: Value | C16: Formula | D16: What it is / Python source
A17: Beta | B17: {=(SUMPRODUCT(IF('10 Portfolio Returns'!$B$5:$B$723="",0,'10 Portfolio Returns'!$B$5:$B$723-AVERAGE('10 Portfolio Returns'!$B$5:$B$723)),IF('05 Simple Returns'!$H$5:$H$723="",0,'05 Simple Returns'!$H$5:$H$723-AVERAGE('05 Simple Returns'!$H$5:$H$723)))/(COUNT('10 Portfolio Returns'!$B$5:$B$723)-1))/(SUMPRODUCT(IF('05 Simple Returns'!$H$5:$H$723="",0,'05 Simple Returns'!$H$5:$H$723-AVERAGE('05 Simple Returns'!$H$5:$H$723)),IF('05 Simple Returns'!$H$5:$H$723="",0,'05 Simple Returns'!$H$5:$H$723-AVERAGE('05 Simple Returns'!$H$5:$H$723)))/(COUNT('05 Simple Returns'!$H$5:$H$723)-1))} | C17: Cov(portfolio, benchmark) / Var(benchmark) | D17: Sensitivity to the market. Beta of 1 moves with the index; below 1 is defensive. Sample covariance (n-1) to match numpy's np.cov default. Python: risk_metrics.beta().
A18: Daily risk-free rate | B18: ='02 Config'!$B$10/'02 Config'!$B$12 | C18: annual risk-free / 252 | D18: The annual input rate de-annualised, because alpha is computed on daily data first.
A19: Alpha (annualised) | B19: =(AVERAGE('10 Portfolio Returns'!$B$5:$B$723)-(B18+B17*(AVERAGE('05 Simple Returns'!$H$5:$H$723)-B18)))*'02 Config'!$B$12 | C19: (Rp - [Rf + Beta x (Rm - Rf)]) x 252 | D19: Jensen's alpha: return earned beyond what CAPM says the portfolio's beta entitles it to. Positive alpha is skill (or unmeasured risk). Computed daily then annualised by multiplication, exactly as risk_metrics.alpha() does.
A22: RISK-ADJUSTED PERFORMANCE RATIOS
A23: Metric | B23: Value | C23: Formula | D23: What it is / Python source
A24: Sharpe ratio | B24: =(B8-'02 Config'!$B$10)/B12 | C24: (Rp - Rf) / annual volatility | D24: Excess return per unit of TOTAL risk. The standard cross-portfolio comparison. Python: risk_metrics.sharpe_ratio().
A25: Downside deviation (daily) | B25: {=SQRT(SUMPRODUCT(IF('10 Portfolio Returns'!$B$5:$B$723="",0,IF('10 Portfolio Returns'!$B$5:$B$723<0,('10 Portfolio Returns'!$B$5:$B$723-AVERAGEIF('10 Portfolio Returns'!$B$5:$B$723,"<0"))^2,0)))/COUNTIF('10 Portfolio Returns'!$B$5:$B$723,"<0"))} | C25: population std. dev. of negative days only | D25: Only losses count as risk. Population (divide by n) to match np.std(). Python: risk_metrics.downside_deviation().
A26: Sortino ratio | B26: =(B8-'02 Config'!$B$10)/B25 | C26: (Rp - Rf) / DAILY downside deviation | D26: Sharpe but penalising only downside volatility. NOTE: this divides an ANNUAL excess return by a DAILY downside deviation, which inflates it by roughly SQRT(252). That is not a mistake — risk_metrics.sortino_ratio() deliberately mirrors the original notebook. Multiply cell B25 by SQRT(252) first for the conventional figure.
A27: Maximum drawdown | B27: =MAX('10 Portfolio Returns'!$F$5:$F$723) | C27: MAX of the drawdown column | D27: Worst peak-to-trough fall in the cumulative growth path — the loss an investor who bought the high would have lived through. Python: risk_metrics.max_drawdown().
A28: Calmar ratio | B28: =B8/B27 | C28: annual return / max drawdown | D28: Return per unit of worst-case pain. Python: risk_metrics.calmar_ratio().
A29: Treynor ratio | B29: =(B8-'02 Config'!$B$10)/B17 | C29: (Rp - Rf) / Beta | D29: Excess return per unit of SYSTEMATIC risk. Sharpe divides by total risk, Treynor by market risk only — the right measure when the portfolio is one sleeve inside a diversified whole. Python: risk_metrics.treynor_ratio().
A32: VALUE AT RISK & EXPECTED SHORTFALL
A33: One-day horizon, historical (non-parametric) method. Losses are shown as negative numbers, scaled by the portfolio value on sheet '02 Config'.
A34: Confidence level | B34: Percentile used | C34: VaR (return) | D34: VaR ($) | E34: CVaR (return) | F34: CVaR ($)
A35: ='02 Config'!$B$13 | B35: =1-A35 | C35: =PERCENTILE('10 Portfolio Returns'!$B$5:$B$723,B35) | D35: =C35*'02 Config'!$B$11 | E35: =AVERAGEIF('10 Portfolio Returns'!$B$5:$B$723,"<="&C35) | F35: =E35*'02 Config'!$B$11
A36: ='02 Config'!$B$14 | B36: =1-A36 | C36: =PERCENTILE('10 Portfolio Returns'!$B$5:$B$723,B36) | D36: =C36*'02 Config'!$B$11 | E36: =AVERAGEIF('10 Portfolio Returns'!$B$5:$B$723,"<="&C36) | F36: =E36*'02 Config'!$B$11
A37: ='02 Config'!$B$15 | B37: =1-A37 | C37: =PERCENTILE('10 Portfolio Returns'!$B$5:$B$723,B37) | D37: =C37*'02 Config'!$B$11 | E37: =AVERAGEIF('10 Portfolio Returns'!$B$5:$B$723,"<="&C37) | F37: =E37*'02 Config'!$B$11
A40: Portfolio weights used throughout (minimum variance, from sheet '08 Optimisation')
A41: JPM | B41: ='08 Optimisation'!$B$36
A42: MS | B42: ='08 Optimisation'!$B$37
A43: BAC | B43: ='08 Optimisation'!$B$38
A44: AAPL | B44: ='08 Optimisation'!$B$39
A45: MSFT | B45: ='08 Optimisation'!$B$40
A46: GLD | B46: ='08 Optimisation'!$B$41

Sheet 12 Charts
A1: Charts
A2: The two figures main.py writes out as HTML, plus the cumulative growth and drawdown paths.
A3: Mirrors: visualization.py -> plot_prices(), plot_efficient_frontier()
A5: Helper cells for the marker points plotted below
A6: Min-variance volatility | B6: ='08 Optimisation'!$B$44
A7: Min-variance return | B7: ='08 Optimisation'!$B$43
A8: Tangency volatility | B8: ='08 Optimisation'!$B$58
A9: Tangency return | B9: ='08 Optimisation'!$B$57
